Workbook

Sheet Materiais_Estoque
B4: SKU | C4: CATEGÓRIA | D4: DESCRIÇÃO | E4: UNID. MEDIDA | F4: ESTOQUE ATUAL | G4: CONSUMO MÉDIO MENSAL | H4: CURVA ABC | I4: ITEM ESSENCIAL | J4: VALOR UNIT. (R$) | K4: VALOR TOTAL (R$) | L4: NF-e | M4: FORNECEDOR
B5: 20814 | C5: Copa | D5: AÇÚCAR (UNID) PACOTE 1 KG | E5: Pct | F5: 80 | G5: 50 | H5: A | I5: SIM | J5: 6.8195 | K5: =TBEstoque[[#This Row],[ESTOQUE ATUAL]]*TBEstoque[[#This Row],[VALOR UNIT. (R$)]] -> 545.56 | L5: 946 | M5: FORNECEDOR 01
B6: 20815 | C6: Copa | D6: CAFÉ EM GRÃO MÁQUINA (UNID) | E6: Pct | F6: 200 | G6: 100 | H6: A | I6: SIM | J6: 97.75 | K6: =TBEstoque[[#This Row],[ESTOQUE ATUAL]]*TBEstoque[[#This Row],[VALOR UNIT. (R$)]] -> 19550 | L6: 15295 | M6: FORNECEDOR 02
B7: 20816 | C7: Copa | D7: CAFÉ EM PÓ (UNID) PACOTE 500 GRAMAS | E7: Pct | F7: 70 | G7: 40 | H7: B | I7: NÃO | J7: 51.635 | K7: =TBEstoque[[#This Row],[ESTOQUE ATUAL]]*TBEstoque[[#This Row],[VALOR UNIT. (R$)]] -> 3614.45 | L7: 897 | M7: FORNECEDOR 03
B8: 20817 | C8: Copa | D8: CHOCOLATE EM PÓ 1KG (UNID) | E8: Pct | F8: 200 | G8: 120 | H8: A | I8: SIM | J8: 63.25 | K8: =TBEstoque[[#This Row],[ESTOQUE ATUAL]]*TBEstoque[[#This Row],[VALOR UNIT. (R$)]] -> 12650 | L8: 15295 | M8: FORNECEDOR 04
B9: 20818 | C9: Copa | D9: COPO DESCARTÁVEL 160ML (PCT) | E9: Pct | F9: 50 | G9: 20 | H9: C | I9: NÃO | J9: 9.9935 | K9: =TBEstoque[[#This Row],[ESTOQUE ATUAL]]*TBEstoque[[#This Row],[VALOR UNIT. (R$)]] -> 499.675 | L9: 946 | M9: FORNECEDOR 05
B10: 20819 | C10: Copa | D10: COPO DESCARTÁVEL 180ML (PCT) | E10: Pct | F10: 150 | G10: 50 | H10: B | I10: SIM | J10: 10.0395 | K10: =TBEstoque[[#This Row],[ESTOQUE ATUAL]]*TBEstoque[[#This Row],[VALOR UNIT. (R$)]] -> 1505.925 | L10: 897 | M10: FORNECEDOR 06
B11: 20820 | C11: Copa | D11: COPO DESCARTÁVEL 80ML (PCT) | E11: Pct | F11: 30 | G11: 10 | H11: C | I11: NÃO | J11: 4.99 | K11: =TBEstoque[[#This Row],[ESTOQUE ATUAL]]*TBEstoque[[#This Row],[VALOR UNIT. (R$)]] -> 149.7 | L11: 997 | M11: FORNECEDOR 07
B12: 20821 | C12: Copa | D12: LEITE EM PÓ 400 G (UNID) | E12: Pct | F12: 300 | G12: 200 | H12: A | I12: SIM | J12: 27.6 | K12: =TBEstoque[[#This Row],[ESTOQUE ATUAL]]*TBEstoque[[#This Row],[VALOR UNIT. (R$)]] -> 8280 | L12: 15295 | M12: FORNECEDOR 08
B13: 832 | C13: Expedição | D13: ÁGUA DESMINERALIZADA 5 LT | E13: Gl | F13: 10 | G13: 1 | H13: B | I13: SIM | J13: 0 | K13: =TBEstoque[[#This Row],[ESTOQUE ATUAL]]*TBEstoque[[#This Row],[VALOR UNIT. (R$)]] -> 0 | L13: 998 | M13: FORNECEDOR 09
B14: 20822 | C14: Expedição | D14: BOBINA MANTA BOLHA ALMOFADA MAQUINA WORLD POST (UNID) | E14: Unid | F14: 15 | G14: 5 | H14: B | I14: SIM | J14: 230 | K14: =TBEstoque[[#This Row],[ESTOQUE ATUAL]]*TBEstoque[[#This Row],[VALOR UNIT. (R$)]] -> 3450 | L14: 130064 | M14: FORNECEDOR 10
B15: 20824 | C15: Expedição | D15: CAIXA PAPELÃO PARDA Nº00 (UNID) | E15: Unid | F15: 20000 | G15: 10000 | H15: A | I15: SIM | J15: 1.081 | K15: =TBEstoque[[#This Row],[ESTOQUE ATUAL]]*TBEstoque[[#This Row],[VALOR UNIT. (R$)]] -> 21620 | L15: 33390 | M15: FORNECEDOR 11
B16: 20825 | C16: Expedição | D16: CAIXA PAPELÃO PARDA Nº01 (UNID) | E16: Unid | F16: 18000 | G16: 8000 | H16: A | I16: SIM | J16: 0.897 | K16: =TBEstoque[[#This Row],[ESTOQUE ATUAL]]*TBEstoque[[#This Row],[VALOR UNIT. (R$)]] -> 16146 | L16: 33644 | M16: FORNECEDOR 12
... B71: 20811 | C71: Geral | D71: FOLHA DE SULFITE A5 PACOTE | E71: Pct | F71: 70 | G71: 75 | H71: B | I71: NÃO | J71: 14.3175 | K71: =TBEstoque[[#This Row],[ESTOQUE ATUAL]]*TBEstoque[[#This Row],[VALOR UNIT. (R$)]] -> 1002.225 | L71: 37184 | M71: FORNECEDOR 03
B72: 20847 | C72: Limpeza | D72: ÁGUA SANITARIA SUPER CANDIDA GALÃO 5 LTS | E72: Gl | F72: 25 | G72: 15 | H72: B | I72: SIM | J72: 24.84 | K72: =TBEstoque[[#This Row],[ESTOQUE ATUAL]]*TBEstoque[[#This Row],[VALOR UNIT. (R$)]] -> 621 | L72: 950 | M72: FORNECEDOR 03 | O72: 1.15
B73: 926 | C73: Limpeza | D73: BOM AR | E73: Unid | F73: 30 | G73: 15 | H73: B | I73: NÃO | J73: 27.4275 | K73: =TBEstoque[[#This Row],[ESTOQUE ATUAL]]*TBEstoque[[#This Row],[VALOR UNIT. (R$)]] -> 822.825 | L73: 884 | M73: FORNECEDOR 03
B74: 20848 | C74: Limpeza | D74: DESINFETANTE FLORAL GALÃO 5 LTS | E74: Gl | F74: 45 | G74: 30 | H74: A | I74: SIM | J74: 48.9325 | K74: =TBEstoque[[#This Row],[ESTOQUE ATUAL]]*TBEstoque[[#This Row],[VALOR UNIT. (R$)]] -> 2201.9625 | L74: 937 | M74: FORNECEDOR 03
B75: 20849 | C75: Limpeza | D75: DESINFETANTE LAVANDA GALÃO 5 LTS | E75: Gl | F75: 30 | G75: 10 | H75: B | I75: NÃO | J75: 41.653 | K75: =TBEstoque[[#This Row],[ESTOQUE ATUAL]]*TBEstoque[[#This Row],[VALOR UNIT. (R$)]] -> 1249.59 | L75: 950 | M75: FORNECEDOR 03
B76: 20850 | C76: Limpeza | D76: DETERGENTE LÍQUIDO YPÊ CLEAR GALÃO 5L | E76: Gl | F76: 25 | G76: 15 | H76: B | I76: SIM | J76: 35.3625 | K76: =TBEstoque[[#This Row],[ESTOQUE ATUAL]]*TBEstoque[[#This Row],[VALOR UNIT. (R$)]] -> 884.0625 | L76: 950 | M76: FORNECEDOR 03
B77: 20851 | C77: Limpeza | D77: ESPONJA DUPLA FACE 3M (UNI) | E77: Unid | F77: 240 | G77: 120 | H77: A | I77: SIM | J77: 1.955 | K77: =TBEstoque[[#This Row],[ESTOQUE ATUAL]]*TBEstoque[[#This Row],[VALOR UNIT. (R$)]] -> 469.2 | L77: 906 | M77: FORNECEDOR 03
B78: 20852 | C78: Limpeza | D78: FLANELA BRANCA (UNI) | E78: Unid | F78: 90 | G78: 50 | H78: B | I78: NÃO | J78: 2.99 | K78: =TBEstoque[[#This Row],[ESTOQUE ATUAL]]*TBEstoque[[#This Row],[VALOR UNIT. (R$)]] -> 269.1 | L78: 906 | M78: FORNECEDOR 03
B79: 20853 | C79: Limpeza | D79: LUSTRA MÓVEIS POLIFLOR (UNI) | E79: Unid | F79: 32 | G79: 10 | H79: B | I79: NÃO | J79: 32.6025 | K79: =TBEstoque[[#This Row],[ESTOQUE ATUAL]]*TBEstoque[[#This Row],[VALOR UNIT. (R$)]] -> 1043.28 | L79: 906 | M79: FORNECEDOR 03
B80: 20854 | C80: Limpeza | D80: LUVA AMARELA TAM: G (PARES) | E80: Par | F80: 12 | G80: 1 | H80: C | I80: NÃO | J80: 14.03 | K80: =TBEstoque[[#This Row],[ESTOQUE ATUAL]]*TBEstoque[[#This Row],[VALOR UNIT. (R$)]] -> 168.36 | L80: 897 | M80: FORNECEDOR 03
B81: 20855 | C81: Limpeza | D81: LUVA AMARELA TAM: GG (PARES) | E81: Par | F81: 8 | G81: 0 | H81: C | I81: NÃO | J81: 16.5255 | K81: =TBEstoque[[#This Row],[ESTOQUE ATUAL]]*TBEstoque[[#This Row],[VALOR UNIT. (R$)]] -> 132.204 | L81: 897 | M81: FORNECEDOR 03
B82: 20856 | C82: Limpeza | D82: LUVA AMARELA TAM: M (PARES) | E82: Par | F82: 24 | G82: 2 | H82: B | I82: SIM | J82: 13.8 | K82: =TBEstoque[[#This Row],[ESTOQUE ATUAL]]*TBEstoque[[#This Row],[VALOR UNIT. (R$)]] -> 331.2 | L82: 937 | M82: FORNECEDOR 03
B83: 20857 | C83: Limpeza | D83: LUVA AMARELA TAM: P (PARES) | E83: Par | F83: 16 | G83: 5 | H83: B | I83: SIM | J83: 14.03 | K83: =TBEstoque[[#This Row],[ESTOQUE ATUAL]]*TBEstoque[[#This Row],[VALOR UNIT. (R$)]] -> 224.48 | L83: 897 | M83: FORNECEDOR 03
B84: 20858 | C84: Limpeza | D84: LUVA AZUL TAM: G (PARES) | E84: Par | F84: 12 | G84: 2 | H84: C | I84: NÃO | J84: 18.63 | K84: =TBEstoque[[#This Row],[ESTOQUE ATUAL]]*TBEstoque[[#This Row],[VALOR UNIT. (R$)]] -> 223.56 | L84: 897 | M84: FORNECEDOR 03
... B108: 20880 | C108: Limpeza | D108: VEJA MULTIUSO (UNI) | E108: Unid | F108: 50 | G108: 30 | H108: A | I108: SIM | J108: 9.1425 | K108: =TBEstoque[[#This Row],[ESTOQUE ATUAL]]*TBEstoque[[#This Row],[VALOR UNIT. (R$)]] -> 457.125 | L108: 961 | M108: FORNECEDOR 03

Sheet Consumo_Mensal
B4: ID PEDIDO | C4: SKU | D4: CATEGÓRIA | E4: DESCRIÇÃO | F4: QTDE SOLICITADA | G4: UNID. MEDIDA | H4: UNID. DESTINO | I4: SOLICITANTE | J4: DATA SOLICITADA | K4: DATA MOVIMENTADA | L4: LEAD TIME (DIAS) | M4: VALOR TOTAL (R$)
B5: ="PED-" & Consumo_Mensal!$H5 & "-" & TEXT(Consumo_Mensal!$J5, "ddmmaa") -> PED-CD Logística - Regional ABC-090226 | C5: 20817 | D5: Copa | E5: CHOCOLATE EM PÓ 1KG (UNID) | F5: 3 | G5: Pct | H5: CD Logística - Regional ABC | I5: Auxiliar Operacional 01 | J5: 46062 | K5: 46063 | L5: =CONCATENATE(NETWORKDAYS(Consumo_Mensal!$J5, Consumo_Mensal!$K5)-1, " dia") -> 1 dia | M5: =IFERROR(Consumo_Mensal!$F5*VLOOKUP(Consumo_Mensal!$E5,TBEstoque[[DESCRIÇÃO]:[VALOR UNIT. (R$)]],7,0), 0) -> 189.75
B6: ="PED-" & Consumo_Mensal!$H6 & "-" & TEXT(Consumo_Mensal!$J6, "ddmmaa") -> PED-CD Logística - Regional ABC-090226 | C6: 20815 | D6: Copa | E6: CAFÉ EM GRÃO MÁQUINA (UNID) | F6: 1 | G6: Pct | H6: CD Logística - Regional ABC | I6: Auxiliar Operacional 01 | J6: 46062 | K6: 46063 | L6: =CONCATENATE(NETWORKDAYS(Consumo_Mensal!$J6, Consumo_Mensal!$K6)-1, " dia") -> 1 dia | M6: =IFERROR(Consumo_Mensal!$F6*VLOOKUP(Consumo_Mensal!$E6,TBEstoque[[DESCRIÇÃO]:[VALOR UNIT. (R$)]],7,0), 0) -> 97.75
B7: ="PED-" & Consumo_Mensal!$H7 & "-" & TEXT(Consumo_Mensal!$J7, "ddmmaa") -> PED-CD Logística - Regional ABC-090226 | C7: 20821 | D7: Copa | E7: LEITE EM PÓ 400 G (UNID) | F7: 1 | G7: Pct | H7: CD Logística - Regional ABC | I7: Auxiliar Operacional 01 | J7: 46062 | K7: 46063 | L7: =CONCATENATE(NETWORKDAYS(Consumo_Mensal!$J7, Consumo_Mensal!$K7)-1, " dia") -> 1 dia | M7: =IFERROR(Consumo_Mensal!$F7*VLOOKUP(Consumo_Mensal!$E7,TBEstoque[[DESCRIÇÃO]:[VALOR UNIT. (R$)]],7,0), 0) -> 27.6
B8: ="PED-" & Consumo_Mensal!$H8 & "-" & TEXT(Consumo_Mensal!$J8, "ddmmaa") -> PED-Farmácia Principal - Unidade 01-090226 | C8: 20814 | D8: Copa | E8: AÇÚCAR (UNID) PACOTE 1 KG | F8: 1 | G8: Pct | H8: Farmácia Principal - Unidade 01 | I8: Assistente Administrativo 01 | J8: 46062 | K8: 46063 | L8: =CONCATENATE(NETWORKDAYS(Consumo_Mensal!$J8, Consumo_Mensal!$K8)-1, " dia") -> 1 dia | M8: =IFERROR(Consumo_Mensal!$F8*VLOOKUP(Consumo_Mensal!$E8,TBEstoque[[DESCRIÇÃO]:[VALOR UNIT. (R$)]],7,0), 0) -> 6.8195
B9: ="PED-" & Consumo_Mensal!$H9 & "-" & TEXT(Consumo_Mensal!$J9, "ddmmaa") -> PED-Farmácia Principal - Unidade 01-090226 | C9: 20815 | D9: Copa | E9: CAFÉ EM GRÃO MÁQUINA (UNID) | F9: 3 | G9: Pct | H9: Farmácia Principal - Unidade 01 | I9: Assistente Administrativo 01 | J9: 46062 | K9: 46063 | L9: =CONCATENATE(NETWORKDAYS(Consumo_Mensal!$J9, Consumo_Mensal!$K9)-1, " dia") -> 1 dia | M9: =IFERROR(Consumo_Mensal!$F9*VLOOKUP(Consumo_Mensal!$E9,TBEstoque[[DESCRIÇÃO]:[VALOR UNIT. (R$)]],7,0), 0) -> 293.25
B10: ="PED-" & Consumo_Mensal!$H10 & "-" & TEXT(Consumo_Mensal!$J10, "ddmmaa") -> PED-Farmácia Principal - Unidade 01-090226 | C10: 20817 | D10: Copa | E10: CHOCOLATE EM PÓ 1KG (UNID) | F10: 3 | G10: Pct | H10: Farmácia Principal - Unidade 01 | I10: Assistente Administrativo 01 | J10: 46062 | K10: 46063 | L10: =CONCATENATE(NETWORKDAYS(Consumo_Mensal!$J10, Consumo_Mensal!$K10)-1, " dia") -> 1 dia | M10: =IFERROR(Consumo_Mensal!$F10*VLOOKUP(Consumo_Mensal!$E10,TBEstoque[[DESCRIÇÃO]:[VALOR UNIT. (R$)]],7,0), 0) -> 189.75
B11: ="PED-" & Consumo_Mensal!$H11 & "-" & TEXT(Consumo_Mensal!$J11, "ddmmaa") -> PED-Farmácia Principal - Unidade 01-090226 | C11: 20819 | D11: Copa | E11: COPO DESCARTÁVEL 180ML (PCT) | F11: 5 | G11: Pct | H11: Farmácia Principal - Unidade 01 | I11: Assistente Administrativo 01 | J11: 46062 | K11: 46063 | L11: =CONCATENATE(NETWORKDAYS(Consumo_Mensal!$J11, Consumo_Mensal!$K11)-1, " dia") -> 1 dia | M11: =IFERROR(Consumo_Mensal!$F11*VLOOKUP(Consumo_Mensal!$E11,TBEstoque[[DESCRIÇÃO]:[VALOR UNIT. (R$)]],7,0), 0) -> 50.1975
B12: ="PED-" & Consumo_Mensal!$H12 & "-" & TEXT(Consumo_Mensal!$J12, "ddmmaa") -> PED-Farmácia Principal - Unidade 01-090226 | C12: 20821 | D12: Copa | E12: LEITE EM PÓ 400 G (UNID) | F12: 4 | G12: Pct | H12: Farmácia Principal - Unidade 01 | I12: Assistente Administrativo 01 | J12: 46062 | K12: 46063 | L12: =CONCATENATE(NETWORKDAYS(Consumo_Mensal!$J12, Consumo_Mensal!$K12)-1, " dia") -> 1 dia | M12: =IFERROR(Consumo_Mensal!$F12*VLOOKUP(Consumo_Mensal!$E12,TBEstoque[[DESCRIÇÃO]:[VALOR UNIT. (R$)]],7,0), 0) -> 110.4
B13: ="PED-" & Consumo_Mensal!$H13 & "-" & TEXT(Consumo_Mensal!$J13, "ddmmaa") -> PED-Farmácia Satélite - Unidade 02-100226 | C13: 20821 | D13: Copa | E13: LEITE EM PÓ 400 G (UNID) | F13: 3 | G13: Pct | H13: Farmácia Satélite - Unidade 02 | I13: Farmacêutico Pleno 01 | J13: 46063 | K13: 46064 | L13: =CONCATENATE(NETWORKDAYS(Consumo_Mensal!$J13, Consumo_Mensal!$K13)-1, " dia") -> 1 dia | M13: =IFERROR(Consumo_Mensal!$F13*VLOOKUP(Consumo_Mensal!$E13,TBEstoque[[DESCRIÇÃO]:[VALOR UNIT. (R$)]],7,0), 0) -> 82.8
B14: ="PED-" & Consumo_Mensal!$H14 & "-" & TEXT(Consumo_Mensal!$J14, "ddmmaa") -> PED-Farmácia Satélite - Unidade 02-100226 | C14: 20815 | D14: Copa | E14: CAFÉ EM GRÃO MÁQUINA (UNID) | F14: 1 | G14: Pct | H14: Farmácia Satélite - Unidade 02 | I14: Farmacêutico Pleno 01 | J14: 46063 | K14: 46064 | L14: =CONCATENATE(NETWORKDAYS(Consumo_Mensal!$J14, Consumo_Mensal!$K14)-1, " dia") -> 1 dia | M14: =IFERROR(Consumo_Mensal!$F14*VLOOKUP(Consumo_Mensal!$E14,TBEstoque[[DESCRIÇÃO]:[VALOR UNIT. (R$)]],7,0), 0) -> 97.75
B15: ="PED-" & Consumo_Mensal!$H15 & "-" & TEXT(Consumo_Mensal!$J15, "ddmmaa") -> PED-Farmácia Satélite - Unidade 02-100226 | C15: 20814 | D15: Copa | E15: AÇÚCAR (UNID) PACOTE 1 KG | F15: 1 | G15: Pct | H15: Farmácia Satélite - Unidade 02 | I15: Farmacêutico Pleno 01 | J15: 46063 | K15: 46064 | L15: =CONCATENATE(NETWORKDAYS(Consumo_Mensal!$J15, Consumo_Mensal!$K15)-1, " dia") -> 1 dia | M15: =IFERROR(Consumo_Mensal!$F15*VLOOKUP(Consumo_Mensal!$E15,TBEstoque[[DESCRIÇÃO]:[VALOR UNIT. (R$)]],7,0), 0) -> 6.8195
B16: ="PED-" & Consumo_Mensal!$H16 & "-" & TEXT(Consumo_Mensal!$J16, "ddmmaa") -> PED-Farmácia Satélite - Unidade 03-100226 | C16: 20819 | D16: Copa | E16: COPO DESCARTÁVEL 180ML (PCT) | F16: 1 | G16: Pct | H16: Farmácia Satélite - Unidade 03 | I16: Farmacêutico Pleno 02 | J16: 46063 | K16: 46064 | L16: =CONCATENATE(NETWORKDAYS(Consumo_Mensal!$J16, Consumo_Mensal!$K16)-1, " dia") -> 1 dia | M16: =IFERROR(Consumo_Mensal!$F16*VLOOKUP(Consumo_Mensal!$E16,TBEstoque[[DESCRIÇÃO]:[VALOR UNIT. (R$)]],7,0), 0) -> 10.0395
... B130: ="PED-" & Consumo_Mensal!$H130 & "-" & TEXT(Consumo_Mensal!$J130, "ddmmaa") -> PED-Farmácia Satélite - Unidade 05-040326 | C130: 20826 | D130: Expedição | E130: CAIXA PAPELÃO PARDA Nº02 (UNID) | F130: 50 | G130: Fd C/ 25 Unid | H130: Farmácia Satélite - Unidade 05 | I130: Assistente Administrativo 03 | J130: 46085 | K130: 46086 | L130: =CONCATENATE(NETWORKDAYS(Consumo_Mensal!$J130, Consumo_Mensal!$K130)-1, " dia") -> 1 dia | M130: =IFERROR(Consumo_Mensal!$F130*VLOOKUP(Consumo_Mensal!$E130,TBEstoque[[DESCRIÇÃO]:[VALOR UNIT. (R$)]],7,0), 0) -> 68.425
B131: ="PED-" & Consumo_Mensal!$H131 & "-" & TEXT(Consumo_Mensal!$J131, "ddmmaa") -> PED-Farmácia Satélite - Unidade 05-040326 | C131: =INDEX(Materiais_Estoque!$B$5:$B$104, MATCH(TBConsumo[[#This Row],[DESCRIÇÃO]], Materiais_Estoque!$D$5:$D$104, 0)) -> 20910 | D131: Expedição | E131: CAIXA PAPELÃO PARDA Nº05 (UNID) | F131: 50 | G131: Fd C/ 10 Unid | H131: Farmácia Satélite - Unidade 05 | I131: Assistente Administrativo 03 | J131: 46085 | K131: 46086 | L131: =CONCATENATE(NETWORKDAYS(Consumo_Mensal!$J131, Consumo_Mensal!$K131)-1, " dia") -> 1 dia | M131: =IFERROR(Consumo_Mensal!$F131*VLOOKUP(Consumo_Mensal!$E131,TBEstoque[[DESCRIÇÃO]:[VALOR UNIT. (R$)]],7,0), 0) -> 277.15
B132: ="PED-" & Consumo_Mensal!$H132 & "-" & TEXT(Consumo_Mensal!$J132, "ddmmaa") -> PED-Planta Industrial - Suprimentos-050326 | C132: 20846 | D132: Expedição | E132: FITA TRANSPARENTE 48 X 100M (UNI) | F132: 24 | G132: Unid | H132: Planta Industrial - Suprimentos | I132: Almoxarife Jr | J132: 46086 | K132: 46087 | L132: =CONCATENATE(NETWORKDAYS(Consumo_Mensal!$J132, Consumo_Mensal!$K132)-1, " dia") -> 1 dia | M132: =IFERROR(Consumo_Mensal!$F132*VLOOKUP(Consumo_Mensal!$E132,TBEstoque[[DESCRIÇÃO]:[VALOR UNIT. (R$)]],7,0), 0) -> 42.228
B133: ="PED-" & Consumo_Mensal!$H133 & "-" & TEXT(Consumo_Mensal!$J133, "ddmmaa") -> PED-Farmácia Principal - Unidade 01-090326 | C133: 20833 | D133: Expedição | E133: ENVELOPE COM BOLHA P (UNID) | F133: 75 | G133: Fd C/ 25 Unid | H133: Farmácia Principal - Unidade 01 | I133: Assistente Administrativo 02 | J133: 46090 | K133: 46090 | L133: =CONCATENATE(NETWORKDAYS(Consumo_Mensal!$J133, Consumo_Mensal!$K133)-1, " dia") -> 0 dia | M133: =IFERROR(Consumo_Mensal!$F133*VLOOKUP(Consumo_Mensal!$E133,TBEstoque[[DESCRIÇÃO]:[VALOR UNIT. (R$)]],7,0), 0) -> 38.8125
B134: ="PED-" & Consumo_Mensal!$H134 & "-" & TEXT(Consumo_Mensal!$J134, "ddmmaa") -> PED-Farmácia Principal - Unidade 01-090326 | C134: 20846 | D134: Expedição | E134: FITA TRANSPARENTE 48 X 100M (UNI) | F134: 3 | G134: Unid | H134: Farmácia Principal - Unidade 01 | I134: Assistente Administrativo 02 | J134: 46090 | K134: 46090 | L134: =CONCATENATE(NETWORKDAYS(Consumo_Mensal!$J134, Consumo_Mensal!$K134)-1, " dia") -> 0 dia | M134: =IFERROR(Consumo_Mensal!$F134*VLOOKUP(Consumo_Mensal!$E134,TBEstoque[[DESCRIÇÃO]:[VALOR UNIT. (R$)]],7,0), 0) -> 5.2785
B135: ="PED-" & Consumo_Mensal!$H135 & "-" & TEXT(Consumo_Mensal!$J135, "ddmmaa") -> PED-Farmácia Satélite - Unidade 02-090326 | C135: 20833 | D135: Expedição | E135: ENVELOPE COM BOLHA P (UNID) | F135: 100 | G135: Fd C/ 25 Unid | H135: Farmácia Satélite - Unidade 02 | I135: Farmacêutico Pleno 01 | J135: 46090 | K135: 46091 | L135: =CONCATENATE(NETWORKDAYS(Consumo_Mensal!$J135, Consumo_Mensal!$K135)-1, " dia") -> 1 dia | M135: =IFERROR(Consumo_Mensal!$F135*VLOOKUP(Consumo_Mensal!$E135,TBEstoque[[DESCRIÇÃO]:[VALOR UNIT. (R$)]],7,0), 0) -> 51.75
B136: ="PED-" & Consumo_Mensal!$H136 & "-" & TEXT(Consumo_Mensal!$J136, "ddmmaa") -> PED-Farmácia Satélite - Unidade 02-090326 | C136: 20832 | D136: Expedição | E136: ENVELOPE COM BOLHA M (UNID) | F136: 100 | G136: Fd C/ 25 Unid | H136: Farmácia Satélite - Unidade 02 | I136: Farmacêutico Pleno 01 | J136: 46090 | K136: 46091 | L136: =CONCATENATE(NETWORKDAYS(Consumo_Mensal!$J136, Consumo_Mensal!$K136)-1, " dia") -> 1 dia | M136: =IFERROR(Consumo_Mensal!$F136*VLOOKUP(Consumo_Mensal!$E136,TBEstoque[[DESCRIÇÃO]:[VALOR UNIT. (R$)]],7,0), 0) -> 83.95
B137: ="PED-" & Consumo_Mensal!$H137 & "-" & TEXT(Consumo_Mensal!$J137, "ddmmaa") -> PED-Farmácia Satélite - Unidade 02-090326 | C137: 20827 | D137: Expedição | E137: CAIXA PAPELÃO PARDA Nº03 (UNID) | F137: 10 | G137: Fd C/ 10 Unid | H137: Farmácia Satélite - Unidade 02 | I137: Farmacêutico Pleno 01 | J137: 46090 | K137: 46091 | L137: =CONCATENATE(NETWORKDAYS(Consumo_Mensal!$J137, Consumo_Mensal!$K137)-1, " dia") -> 1 dia | M137: =IFERROR(Consumo_Mensal!$F137*VLOOKUP(Consumo_Mensal!$E137,TBEstoque[[DESCRIÇÃO]:[VALOR UNIT. (R$)]],7,0), 0) -> 33.35
B138: ="PED-" & Consumo_Mensal!$H138 & "-" & TEXT(Consumo_Mensal!$J138, "ddmmaa") -> PED-Farmácia Satélite - Unidade 05-110326 | C138: =INDEX(Materiais_Estoque!$B$5:$B$104, MATCH(TBConsumo[[#This Row],[DESCRIÇÃO]], Materiais_Estoque!$D$5:$D$104, 0)) -> 20910 | D138: Expedição | E138: CAIXA PAPELÃO PARDA Nº05 (UNID) | F138: 50 | G138: Fd C/ 10 Unid | H138: Farmácia Satélite - Unidade 05 | I138: Assistente Administrativo 03 | J138: 46092 | K138: 46093 | L138: =CONCATENATE(NETWORKDAYS(Consumo_Mensal!$J138, Consumo_Mensal!$K138)-1, " dia") -> 1 dia | M138: =IFERROR(Consumo_Mensal!$F138*VLOOKUP(Consumo_Mensal!$E138,TBEstoque[[DESCRIÇÃO]:[VALOR UNIT. (R$)]],7,0), 0) -> 277.15
B139: ="PED-" & Consumo_Mensal!$H139 & "-" & TEXT(Consumo_Mensal!$J139, "ddmmaa") -> PED-Farmácia Satélite - Unidade 03-110326 | C139: 20842 | D139: Expedição | E139: GELO AZUL 500ML (UNID) | F139: 1 | G139: Cx | H139: Farmácia Satélite - Unidade 03 | I139: Assistente Administrativo 04 | J139: 46092 | K139: 46093 | L139: =CONCATENATE(NETWORKDAYS(Consumo_Mensal!$J139, Consumo_Mensal!$K139)-1, " dia") -> 1 dia | M139: =IFERROR(Consumo_Mensal!$F139*VLOOKUP(Consumo_Mensal!$E139,TBEstoque[[DESCRIÇÃO]:[VALOR UNIT. (R$)]],7,0), 0) -> 42.5385
B140: ="PED-" & Consumo_Mensal!$H140 & "-" & TEXT(Consumo_Mensal!$J140, "ddmmaa") -> PED-CD Logística - Regional ABC-120326 | C140: 20838 | D140: Expedição | E140: ETIQUETA 100X100 COUCHE ROLO C/350 | F140: 216 | G140: Unid | H140: CD Logística - Regional ABC | I140: Auxiliar de Recebimento | J140: 46093 | K140: 46094 | L140: =CONCATENATE(NETWORKDAYS(Consumo_Mensal!$J140, Consumo_Mensal!$K140)-1, " dia") -> 1 dia | M140: =IFERROR(Consumo_Mensal!$F140*VLOOKUP(Consumo_Mensal!$E140,TBEstoque[[DESCRIÇÃO]:[VALOR UNIT. (R$)]],7,0), 0) -> 5350.536
B141: ="PED-" & Consumo_Mensal!$H141 & "-" & TEXT(Consumo_Mensal!$J141, "ddmmaa") -> PED-Farmácia Principal - Unidade 01-090226 | C141: 20903 | D141: Farmácia/Produção | E141: SONTARA (UNI) | F141: 3 | G141: Unid | H141: Farmácia Principal - Unidade 01 | I141: Assistente Administrativo 01 | J141: 46062 | K141: 46063 | L141: =CONCATENATE(NETWORKDAYS(Consumo_Mensal!$J141, Consumo_Mensal!$K141)-1, " dia") -> 1 dia | M141: =IFERROR(Consumo_Mensal!$F141*VLOOKUP(Consumo_Mensal!$E141,TBEstoque[[DESCRIÇÃO]:[VALOR UNIT. (R$)]],7,0), 0) -> 393.3
B142: ="PED-" & Consumo_Mensal!$H142 & "-" & TEXT(Consumo_Mensal!$J142, "ddmmaa") -> PED-Farmácia Principal - Unidade 01-100226 | C142: 20897 | D142: Farmácia/Produção | E142: LUVA SEM PÓ P LATEX (CX) | F142: 5 | G142: Cx | H142: Farmácia Principal - Unidade 01 | I142: Gestor de Inventário | J142: 46063 | K142: 46064 | L142: =CONCATENATE(NETWORKDAYS(Consumo_Mensal!$J142, Consumo_Mensal!$K142)-1, " dia") -> 1 dia | M142: =IFERROR(Consumo_Mensal!$F142*VLOOKUP(Consumo_Mensal!$E142,TBEstoque[[DESCRIÇÃO]:[VALOR UNIT. (R$)]],7,0), 0) -> 166.75
B143: ="PED-" & Consumo_Mensal!$H143 & "-" & TEXT(Consumo_Mensal!$J143, "ddmmaa") -> PED-Farmácia Principal - Unidade 01-100226 | C143: 20898 | D143: Farmácia/Produção | E143: LUVA SEM PÓ PP LATEX (CX) | F143: 4 | G143: Cx | H143: Farmácia Principal - Unidade 01 | I143: Gestor de Inventário | J143: 46063 | K143: 46064 | L143: =CONCATENATE(NETWORKDAYS(Consumo_Mensal!$J143, Consumo_Mensal!$K143)-1, " dia") -> 1 dia | M143: =IFERROR(Consumo_Mensal!$F143*VLOOKUP(Consumo_Mensal!$E143,TBEstoque[[DESCRIÇÃO]:[VALOR UNIT. (R$)]],7,0), 0) -> 133.4
B144: ="PED-" & Consumo_Mensal!$H144 & "-" & TEXT(Consumo_Mensal!$J144, "ddmmaa") -> PED-Farmácia Principal - Unidade 01-100226 | C144: 20896 | D144: Farmácia/Produção | E144: LUVA SEM PÓ M LATEX (CX) | F144: 4 | G144: Cx | H144: Farmácia Principal - Unidade 01 | I144: Gestor de Inventário | J144: 46063 | K144: 46064 | L144: =CONCATENATE(NETWORKDAYS(Consumo_Mensal!$J144, Consumo_Mensal!$K144)-1, " dia") -> 1 dia | M144: =IFERROR(Consumo_Mensal!$F144*VLOOKUP(Consumo_Mensal!$E144,TBEstoque[[DESCRIÇÃO]:[VALOR UNIT. (R$)]],7,0), 0) -> 133.4
B145: ="PED-" & Consumo_Mensal!$H145 & "-" & TEXT(Consumo_Mensal!$J145, "ddmmaa") -> PED-Farmácia Principal - Unidade 01-100226 | C145: 20984 | D145: Farmácia/Produção | E145: PAPEL MULTIUSO INTERFOLHADO DEMARCARE NEVE | F145: 20 | G145: Pct | H145: Farmácia Principal - Unidade 01 | I145: Gestor de Inventário | J145: 46063 | K145: 46064 | L145: =CONCATENATE(NETWORKDAYS(Consumo_Mensal!$J145, Consumo_Mensal!$K145)-1, " dia") -> 1 dia | M145: =IFERROR(Consumo_Mensal!$F145*VLOOKUP(Consumo_Mensal!$E145,TBEstoque[[DESCRIÇÃO]:[VALOR UNIT. (R$)]],7,0), 0) -> 193.89
B146: ="PED-" & Consumo_Mensal!$H146 & "-" & TEXT(Consumo_Mensal!$J146, "ddmmaa") -> PED-Farmácia Principal - Unidade 01-100226 | C146: 20904 | D146: Farmácia/Produção | E146: TOUCA SANFONADA BRANCO DESCARTÁVEL (PCT C/100) | F146: 10 | G146: Pct | H146: Farmácia Principal - Unidade 01 | I146: Gestor de Inventário | J146: 46063 | K146: 46064 | L146: =CONCATENATE(NETWORKDAYS(Consumo_Mensal!$J146, Consumo_Mensal!$K146)-1, " dia") -> 1 dia | M146: =IFERROR(Consumo_Mensal!$F146*VLOOKUP(Consumo_Mensal!$E146,TBEstoque[[DESCRIÇÃO]:[VALOR UNIT. (R$)]],7,0), 0) -> 103.27
B147: ="PED-" & Consumo_Mensal!$H147 & "-" & TEXT(Consumo_Mensal!$J147, "ddmmaa") -> PED-Farmácia Principal - Unidade 01-100226 | C147: =INDEX(Materiais_Estoque!$B$5:$B$104, MATCH(TBConsumo[[#This Row],[DESCRIÇÃO]], Materiais_Estoque!$D$5:$D$104, 0)) -> 20911 | D147: Farmácia/Produção | E147: ENVELOPE PREMIUN TNT M | F147: 75 | G147: Fd C/ 25 Unid | H147: Farmácia Principal - Unidade 01 | I147: Assistente Administrativo 02 | J147: 46063 | K147: 46064 | L147: =CONCATENATE(NETWORKDAYS(Consumo_Mensal!$J147, Consumo_Mensal!$K147)-1, " dia") -> 1 dia | M147: =IFERROR(Consumo_Mensal!$F147*VLOOKUP(Consumo_Mensal!$E147,TBEstoque[[DESCRIÇÃO]:[VALOR UNIT. (R$)]],7,0), 0) -> 165.6
B148: ="PED-" & Consumo_Mensal!$H148 & "-" & TEXT(Consumo_Mensal!$J148, "ddmmaa") -> PED-Farmácia Principal - Unidade 01-100226 | C148: =INDEX(Materiais_Estoque!$B$5:$B$104, MATCH(TBConsumo[[#This Row],[DESCRIÇÃO]], Materiais_Estoque!$D$5:$D$104, 0)) -> 20912 | D148: Farmácia/Produção | E148: ENVELOPE PREMIUN TNT P | F148: 100 | G148: Fd C/ 25 Unid | H148: Farmácia Principal - Unidade 01 | I148: Assistente Administrativo 02 | J148: 46063 | K148: 46064 | L148: =CONCATENATE(NETWORKDAYS(Consumo_Mensal!$J148, Consumo_Mensal!$K148)-1, " dia") -> 1 dia | M148: =IFERROR(Consumo_Mensal!$F148*VLOOKUP(Consumo_Mensal!$E148,TBEstoque[[DESCRIÇÃO]:[VALOR UNIT. (R$)]],7,0), 0) -> 177.1
B149: ="PED-" & Consumo_Mensal!$H149 & "-" & TEXT(Consumo_Mensal!$J149, "ddmmaa") -> PED-Planta Industrial - Suprimentos-100226 | C149: 20902 | D149: Farmácia/Produção | E149: MÁSCARA TRIPLA DESCARTÁVEL (CAIXA 50 UNI) | F149: 50 | G149: Cx | H149: Planta Industrial - Suprimentos | I149: Almoxarife Jr | J149: 46063 | K149: 46064 | L149: =CONCATENATE(NETWORKDAYS(Consumo_Mensal!$J149, Consumo_Mensal!$K149)-1, " dia") -> 1 dia | M149: =IFERROR(Consumo_Mensal!$F149*VLOOKUP(Consumo_Mensal!$E149,TBEstoque[[DESCRIÇÃO]:[VALOR UNIT. (R$)]],7,0), 0) -> 1667.5
B150: ="PED-" & Consumo_Mensal!$H150 & "-" & TEXT(Consumo_Mensal!$J150, "ddmmaa") -> PED-Escritório Central - Sede-110226 | C150: 20903 | D150: Farmácia/Produção | E150: SONTARA (UNI) | F150: 1 | G150: Unid | H150: Escritório Central - Sede | I150: Secretária Executiva | J150: 46064 | K150: 46065 | L150: =CONCATENATE(NETWORKDAYS(Consumo_Mensal!$J150, Consumo_Mensal!$K150)-1, " dia") -> 1 dia | M150: =IFERROR(Consumo_Mensal!$F150*VLOOKUP(Consumo_Mensal!$E150,TBEstoque[[DESCRIÇÃO]:[VALOR UNIT. (R$)]],7,0), 0) -> 131.1
B151: ="PED-" & Consumo_Mensal!$H151 & "-" & TEXT(Consumo_Mensal!$J151, "ddmmaa") -> PED-Escritório Central - Sede-110226 | C151: 20903 | D151: Farmácia/Produção | E151: SONTARA (UNI) | F151: 1 | G151: Unid | H151: Escritório Central - Sede | I151: Secretária Executiva | J151: 46064 | K151: 46065 | L151: =CONCATENATE(NETWORKDAYS(Consumo_Mensal!$J151, Consumo_Mensal!$K151)-1, " dia") -> 1 dia | M151: =IFERROR(Consumo_Mensal!$F151*VLOOKUP(Consumo_Mensal!$E151,TBEstoque[[DESCRIÇÃO]:[VALOR UNIT. (R$)]],7,0), 0) -> 131.1
B152: ="PED-" & Consumo_Mensal!$H152 & "-" & TEXT(Consumo_Mensal!$J152, "ddmmaa") -> PED-Farmácia Satélite - Unidade 03-120226 | C152: 20901 | D152: Farmácia/Produção | E152: PROPÉ (PCT C/100) | F152: 10 | G152: Pct | H152: Farmácia Satélite - Unidade 03 | I152: Assistente Administrativo 04 | J152: 46065 | K152: 46066 | L152: =CONCATENATE(NETWORKDAYS(Consumo_Mensal!$J152, Consumo_Mensal!$K152)-1, " dia") -> 1 dia | M152: =IFERROR(Consumo_Mensal!$F152*VLOOKUP(Consumo_Mensal!$E152,TBEstoque[[DESCRIÇÃO]:[VALOR UNIT. (R$)]],7,0), 0) -> 138
B153: ="PED-" & Consumo_Mensal!$H153 & "-" & TEXT(Consumo_Mensal!$J153, "ddmmaa") -> PED-Farmácia Satélite - Unidade 03-120226 | C153: 20890 | D153: Farmácia/Produção | E153: AVENTAL DESCARTÁVEL PCT C/ 10 UNIDADES | F153: 5 | G153: Pct | H153: Farmácia Satélite - Unidade 03 | I153: Assistente Administrativo 04 | J153: 46065 | K153: 46066 | L153: =CONCATENATE(NETWORKDAYS(Consumo_Mensal!$J153, Consumo_Mensal!$K153)-1, " dia") -> 1 dia | M153: =IFERROR(Consumo_Mensal!$F153*VLOOKUP(Consumo_Mensal!$E153,TBEstoque[[DESCRIÇÃO]:[VALOR UNIT. (R$)]],7,0), 0) -> 137.9425
B154: ="PED-" & Consumo_Mensal!$H154 & "-" & TEXT(Consumo_Mensal!$J154, "ddmmaa") -> PED-Farmácia Satélite - Unidade 03-120226 | C154: 20904 | D154: Farmácia/Produção | E154: TOUCA SANFONADA BRANCO DESCARTÁVEL (PCT C/100) | F154: 5 | G154: Pct | H154: Farmácia Satélite - Unidade 03 | I154: Assistente Administrativo 04 | J154: 46065 | K154: 46066 | L154: =CONCATENATE(NETWORKDAYS(Consumo_Mensal!$J154, Consumo_Mensal!$K154)-1, " dia") -> 1 dia | M154: =IFERROR(Consumo_Mensal!$F154*VLOOKUP(Consumo_Mensal!$E154,TBEstoque[[DESCRIÇÃO]:[VALOR UNIT. (R$)]],7,0), 0) -> 51.635
B155: ="PED-" & Consumo_Mensal!$H155 & "-" & TEXT(Consumo_Mensal!$J155, "ddmmaa") -> PED-Farmácia Satélite - Unidade 03-120226 | C155: 20903 | D155: Farmácia/Produção | E155: SONTARA (UNI) | F155: 3 | G155: Unid | H155: Farmácia Satélite - Unidade 03 | I155: Assistente Administrativo 04 | J155: 46065 | K155: 46066 | L155: =CONCATENATE(NETWORKDAYS(Consumo_Mensal!$J155, Consumo_Mensal!$K155)-1, " dia") -> 1 dia | M155: =IFERROR(Consumo_Mensal!$F155*VLOOKUP(Consumo_Mensal!$E155,TBEstoque[[DESCRIÇÃO]:[VALOR UNIT. (R$)]],7,0), 0) -> 393.3
B156: ="PED-" & Consumo_Mensal!$H156 & "-" & TEXT(Consumo_Mensal!$J156, "ddmmaa") -> PED-Farmácia Satélite - Unidade 03-120226 | C156: 20984 | D156: Farmácia/Produção | E156: PAPEL MULTIUSO INTERFOLHADO DEMARCARE NEVE | F156: 10 | G156: Pct | H156: Farmácia Satélite - Unidade 03 | I156: Assistente Administrativo 04 | J156: 46065 | K156: 46066 | L156: =CONCATENATE(NETWORKDAYS(Consumo_Mensal!$J156, Consumo_Mensal!$K156)-1, " dia") -> 1 dia | M156: =IFERROR(Consumo_Mensal!$F156*VLOOKUP(Consumo_Mensal!$E156,TBEstoque[[DESCRIÇÃO]:[VALOR UNIT. (R$)]],7,0), 0) -> 96.945
B157: ="PED-" & Consumo_Mensal!$H157 & "-" & TEXT(Consumo_Mensal!$J157, "ddmmaa") -> PED-Farmácia Satélite - Unidade 03-120226 | C157: =INDEX(Materiais_Estoque!$B$5:$B$104, MATCH(TBConsumo[[#This Row],[DESCRIÇÃO]], Materiais_Estoque!$D$5:$D$104, 0)) -> 20912 | D157: Farmácia/Produção | E157: ENVELOPE PREMIUN TNT P | F157: 125 | G157: Fd C/ 25 Unid | H157: Farmácia Satélite - Unidade 03 | I157: Assistente Administrativo 04 | J157: 46065 | K157: 46066 | L157: =CONCATENATE(NETWORKDAYS(Consumo_Mensal!$J157, Consumo_Mensal!$K157)-1, " dia") -> 1 dia | M157: =IFERROR(Consumo_Mensal!$F157*VLOOKUP(Consumo_Mensal!$E157,TBEstoque[[DESCRIÇÃO]:[VALOR UNIT. (R$)]],7,0), 0) -> 221.375
B158: ="PED-" & Consumo_Mensal!$H158 & "-" & TEXT(Consumo_Mensal!$J158, "ddmmaa") -> PED-Farmácia Satélite - Unidade 03-120226 | C158: 20886 | D158: Farmácia/Produção | E158: SACO PLASTICO 15X25 (PCT) | F158: 5 | G158: Kg | H158: Farmácia Satélite - Unidade 03 | I158: Assistente Administrativo 04 | J158: 46065 | K158: 46066 | L158: =CONCATENATE(NETWORKDAYS(Consumo_Mensal!$J158, Consumo_Mensal!$K158)-1, " dia") -> 1 dia | M158: =IFERROR(Consumo_Mensal!$F158*VLOOKUP(Consumo_Mensal!$E158,TBEstoque[[DESCRIÇÃO]:[VALOR UNIT. (R$)]],7,0), 0) -> 120.75
B159: ="PED-" & Consumo_Mensal!$H159 & "-" & TEXT(Consumo_Mensal!$J159, "ddmmaa") -> PED-Farmácia Satélite - Unidade 03-120226 | C159: 20885 | D159: Farmácia/Produção | E159: SACO PLASTICO 10X15 (PCT) | F159: 5 | G159: Kg | H159: Farmácia Satélite - Unidade 03 | I159: Assistente Administrativo 04 | J159: 46065 | K159: 46066 | L159: =CONCATENATE(NETWORKDAYS(Consumo_Mensal!$J159, Consumo_Mensal!$K159)-1, " dia") -> 1 dia | M159: =IFERROR(Consumo_Mensal!$F159*VLOOKUP(Consumo_Mensal!$E159,TBEstoque[[DESCRIÇÃO]:[VALOR UNIT. (R$)]],7,0), 0) -> 120.75
B160: ="PED-" & Consumo_Mensal!$H160 & "-" & TEXT(Consumo_Mensal!$J160, "ddmmaa") -> PED-Farmácia Satélite - Unidade 04-120226 | C160: 20887 | D160: Farmácia/Produção | E160: SACO PLASTICO 20X30 (PCT) | F160: 5 | G160: Kg | H160: Farmácia Satélite - Unidade 04 | I160: Líder de Equipe 01 | J160: 46065 | K160: 46066 | L160: =CONCATENATE(NETWORKDAYS(Consumo_Mensal!$J160, Consumo_Mensal!$K160)-1, " dia") -> 1 dia | M160: =IFERROR(Consumo_Mensal!$F160*VLOOKUP(Consumo_Mensal!$E160,TBEstoque[[DESCRIÇÃO]:[VALOR UNIT. (R$)]],7,0), 0) -> 110.975
B161: ="PED-" & Consumo_Mensal!$H161 & "-" & TEXT(Consumo_Mensal!$J161, "ddmmaa") -> PED-Farmácia Satélite - Unidade 04-120226 | C161: 20888 | D161: Farmácia/Produção | E161: SACO PLASTICO 30X40 (PCT) | F161: 5 | G161: Kg | H161: Farmácia Satélite - Unidade 04 | I161: Líder de Equipe 01 | J161: 46065 | K161: 46066 | L161: =CONCATENATE(NETWORKDAYS(Consumo_Mensal!$J161, Consumo_Mensal!$K161)-1, " dia") -> 1 dia | M161: =IFERROR(Consumo_Mensal!$F161*VLOOKUP(Consumo_Mensal!$E161,TBEstoque[[DESCRIÇÃO]:[VALOR UNIT. (R$)]],7,0), 0) -> 110.975
B162: ="PED-" & Consumo_Mensal!$H162 & "-" & TEXT(Consumo_Mensal!$J162, "ddmmaa") -> PED-Farmácia Satélite - Unidade 04-120226 | C162: =INDEX(Materiais_Estoque!$B$5:$B$104, MATCH(TBConsumo[[#This Row],[DESCRIÇÃO]], Materiais_Estoque!$D$5:$D$104, 0)) -> 20915 | D162: Farmácia/Produção | E162: SACO PLASTICO 40X60 (PCT) | F162: 10 | G162: Kg | H162: Farmácia Satélite - Unidade 04 | I162: Líder de Equipe 01 | J162: 46065 | K162: 46066 | L162: =CONCATENATE(NETWORKDAYS(Consumo_Mensal!$J162, Consumo_Mensal!$K162)-1, " dia") -> 1 dia | M162: =IFERROR(Consumo_Mensal!$F162*VLOOKUP(Consumo_Mensal!$E162,TBEstoque[[DESCRIÇÃO]:[VALOR UNIT. (R$)]],7,0), 0) -> 222
B163: ="PED-" & Consumo_Mensal!$H163 & "-" & TEXT(Consumo_Mensal!$J163, "ddmmaa") -> PED-Farmácia Satélite - Unidade 03-130226 | C163: =INDEX(Materiais_Estoque!$B$5:$B$104, MATCH(TBConsumo[[#This Row],[DESCRIÇÃO]], Materiais_Estoque!$D$5:$D$104, 0)) -> 20916 | D163: Farmácia/Produção | E163: ETIQUETA 50X50 PARA SACHÊ | F163: 30 | G163: Unid | H163: Farmácia Satélite - Unidade 03 | I163: Assistente Administrativo 04 | J163: 46066 | K163: 46069 | L163: =CONCATENATE(NETWORKDAYS(Consumo_Mensal!$J163, Consumo_Mensal!$K163)-1, " dia") -> 1 dia | M163: =IFERROR(Consumo_Mensal!$F163*VLOOKUP(Consumo_Mensal!$E163,TBEstoque[[DESCRIÇÃO]:[VALOR UNIT. (R$)]],7,0), 0) -> 371.4
B164: ="PED-" & Consumo_Mensal!$H164 & "-" & TEXT(Consumo_Mensal!$J164, "ddmmaa") -> PED-Farmácia Satélite - Unidade 03-180226 | C164: 20886 | D164: Farmácia/Produção | E164: SACO PLASTICO 15X25 (PCT) | F164: 5 | G164: Kg | H164: Farmácia Satélite - Unidade 03 | I164: Assistente Administrativo 04 | J164: 46071 | K164: 46072 | L164: =CONCATENATE(NETWORKDAYS(Consumo_Mensal!$J164, Consumo_Mensal!$K164)-1, " dia") -> 1 dia | M164: =IFERROR(Consumo_Mensal!$F164*VLOOKUP(Consumo_Mensal!$E164,TBEstoque[[DESCRIÇÃO]:[VALOR UNIT. (R$)]],7,0), 0) -> 120.75
B165: ="PED-" & Consumo_Mensal!$H165 & "-" & TEXT(Consumo_Mensal!$J165, "ddmmaa") -> PED-Farmácia Satélite - Unidade 02-180226 | C165: =INDEX(Materiais_Estoque!$B$5:$B$104, MATCH(TBConsumo[[#This Row],[DESCRIÇÃO]], Materiais_Estoque!$D$5:$D$104, 0)) -> 20916 | D165: Farmácia/Produção | E165: ETIQUETA 50X50 PARA SACHÊ | F165: 5 | G165: Unid | H165: Farmácia Satélite - Unidade 02 | I165: Farmacêutico Pleno 01 | J165: 46071 | K165: 46072 | L165: =CONCATENATE(NETWORKDAYS(Consumo_Mensal!$J165, Consumo_Mensal!$K165)-1, " dia") -> 1 dia | M165: =IFERROR(Consumo_Mensal!$F165*VLOOKUP(Consumo_Mensal!$E165,TBEstoque[[DESCRIÇÃO]:[VALOR UNIT. (R$)]],7,0), 0) -> 61.9
B166: ="PED-" & Consumo_Mensal!$H166 & "-" & TEXT(Consumo_Mensal!$J166, "ddmmaa") -> PED-Escritório Apoio - Gestão-180226 | C166: 20896 | D166: Farmácia/Produção | E166: LUVA SEM PÓ M LATEX (CX) | F166: 2 | G166: Cx | H166: Escritório Apoio - Gestão | I166: Analista Financeiro | J166: 46071 | K166: 46072 | L166: =CONCATENATE(NETWORKDAYS(Consumo_Mensal!$J166, Consumo_Mensal!$K166)-1, " dia") -> 1 dia | M166: =IFERROR(Consumo_Mensal!$F166*VLOOKUP(Consumo_Mensal!$E166,TBEstoque[[DESCRIÇÃO]:[VALOR UNIT. (R$)]],7,0), 0) -> 66.7
B167: ="PED-" & Consumo_Mensal!$H167 & "-" & TEXT(Consumo_Mensal!$J167, "ddmmaa") -> PED-Farmácia Satélite - Unidade 03-190226 | C167: 20898 | D167: Farmácia/Produção | E167: LUVA SEM PÓ PP LATEX (CX) | F167: 10 | G167: Cx | H167: Farmácia Satélite - Unidade 03 | I167: Assistente Administrativo 04 | J167: 46072 | K167: 46073 | L167: =CONCATENATE(NETWORKDAYS(Consumo_Mensal!$J167, Consumo_Mensal!$K167)-1, " dia") -> 1 dia | M167: =IFERROR(Consumo_Mensal!$F167*VLOOKUP(Consumo_Mensal!$E167,TBEstoque[[DESCRIÇÃO]:[VALOR UNIT. (R$)]],7,0), 0) -> 333.5
B168: ="PED-" & Consumo_Mensal!$H168 & "-" & TEXT(Consumo_Mensal!$J168, "ddmmaa") -> PED-Farmácia Principal - Unidade 01-230226 | C168: 20897 | D168: Farmácia/Produção | E168: LUVA SEM PÓ P LATEX (CX) | F168: 4 | G168: Cx | H168: Farmácia Principal - Unidade 01 | I168: Gestor de Inventário | J168: 46076 | K168: 46076 | L168: =CONCATENATE(NETWORKDAYS(Consumo_Mensal!$J168, Consumo_Mensal!$K168)-1, " dia") -> 0 dia | M168: =IFERROR(Consumo_Mensal!$F168*VLOOKUP(Consumo_Mensal!$E168,TBEstoque[[DESCRIÇÃO]:[VALOR UNIT. (R$)]],7,0), 0) -> 133.4
B169: ="PED-" & Consumo_Mensal!$H169 & "-" & TEXT(Consumo_Mensal!$J169, "ddmmaa") -> PED-Farmácia Principal - Unidade 01-230226 | C169: 20896 | D169: Farmácia/Produção | E169: LUVA SEM PÓ M LATEX (CX) | F169: 3 | G169: Cx | H169: Farmácia Principal - Unidade 01 | I169: Gestor de Inventário | J169: 46076 | K169: 46076 | L169: =CONCATENATE(NETWORKDAYS(Consumo_Mensal!$J169, Consumo_Mensal!$K169)-1, " dia") -> 0 dia | M169: =IFERROR(Consumo_Mensal!$F169*VLOOKUP(Consumo_Mensal!$E169,TBEstoque[[DESCRIÇÃO]:[VALOR UNIT. (R$)]],7,0), 0) -> 100.05
B170: ="PED-" & Consumo_Mensal!$H170 & "-" & TEXT(Consumo_Mensal!$J170, "ddmmaa") -> PED-Farmácia Principal - Unidade 01-230226 | C170: 20984 | D170: Farmácia/Produção | E170: PAPEL MULTIUSO INTERFOLHADO DEMARCARE NEVE | F170: 20 | G170: Pct | H170: Farmácia Principal - Unidade 01 | I170: Gestor de Inventário | J170: 46076 | K170: 46076 | L170: =CONCATENATE(NETWORKDAYS(Consumo_Mensal!$J170, Consumo_Mensal!$K170)-1, " dia") -> 0 dia | M170: =IFERROR(Consumo_Mensal!$F170*VLOOKUP(Consumo_Mensal!$E170,TBEstoque[[DESCRIÇÃO]:[VALOR UNIT. (R$)]],7,0), 0) -> 193.89
B171: ="PED-" & Consumo_Mensal!$H171 & "-" & TEXT(Consumo_Mensal!$J171, "ddmmaa") -> PED-Farmácia Principal - Unidade 01-230226 | C171: 20902 | D171: Farmácia/Produção | E171: MÁSCARA TRIPLA DESCARTÁVEL (CAIXA 50 UNI) | F171: 15 | G171: Pct | H171: Farmácia Principal - Unidade 01 | I171: Gestor de Inventário | J171: 46076 | K171: 46076 | L171: =CONCATENATE(NETWORKDAYS(Consumo_Mensal!$J171, Consumo_Mensal!$K171)-1, " dia") -> 0 dia | M171: =IFERROR(Consumo_Mensal!$F171*VLOOKUP(Consumo_Mensal!$E171,TBEstoque[[DESCRIÇÃO]:[VALOR UNIT. (R$)]],7,0), 0) -> 500.25
B172: ="PED-" & Consumo_Mensal!$H172 & "-" & TEXT(Consumo_Mensal!$J172, "ddmmaa") -> PED-Farmácia Principal - Unidade 01-230226 | C172: 20884 | D172: Farmácia/Produção | E172: RIBBON RESINA ( PCT C/ 2) | F172: 5 | G172: Pct | H172: Farmácia Principal - Unidade 01 | I172: Gestor de Inventário | J172: 46076 | K172: 46076 | L172: =CONCATENATE(NETWORKDAYS(Consumo_Mensal!$J172, Consumo_Mensal!$K172)-1, " dia") -> 0 dia | M172: =IFERROR(Consumo_Mensal!$F172*VLOOKUP(Consumo_Mensal!$E172,TBEstoque[[DESCRIÇÃO]:[VALOR UNIT. (R$)]],7,0), 0) -> 56.35
B173: ="PED-" & Consumo_Mensal!$H173 & "-" & TEXT(Consumo_Mensal!$J173, "ddmmaa") -> PED-Farmácia Principal - Unidade 01-230226 | C173: 20886 | D173: Farmácia/Produção | E173: SACO PLASTICO 15X25 (PCT) | F173: 10 | G173: Kg | H173: Farmácia Principal - Unidade 01 | I173: Gestor de Inventário | J173: 46076 | K173: 46076 | L173: =CONCATENATE(NETWORKDAYS(Consumo_Mensal!$J173, Consumo_Mensal!$K173)-1, " dia") -> 0 dia | M173: =IFERROR(Consumo_Mensal!$F173*VLOOKUP(Consumo_Mensal!$E173,TBEstoque[[DESCRIÇÃO]:[VALOR UNIT. (R$)]],7,0), 0) -> 241.5
B174: ="PED-" & Consumo_Mensal!$H174 & "-" & TEXT(Consumo_Mensal!$J174, "ddmmaa") -> PED-Farmácia Principal - Unidade 01-230226 | C174: 20887 | D174: Farmácia/Produção | E174: SACO PLASTICO 20X30 (PCT) | F174: 5 | G174: Kg | H174: Farmácia Principal - Unidade 01 | I174: Gestor de Inventário | J174: 46076 | K174: 46076 | L174: =CONCATENATE(NETWORKDAYS(Consumo_Mensal!$J174, Consumo_Mensal!$K174)-1, " dia") -> 0 dia | M174: =IFERROR(Consumo_Mensal!$F174*VLOOKUP(Consumo_Mensal!$E174,TBEstoque[[DESCRIÇÃO]:[VALOR UNIT. (R$)]],7,0), 0) -> 110.975
B175: ="PED-" & Consumo_Mensal!$H175 & "-" & TEXT(Consumo_Mensal!$J175, "ddmmaa") -> PED-Farmácia Satélite - Unidade 03-230226 | C175: =INDEX(Materiais_Estoque!$B$5:$B$104, MATCH(TBConsumo[[#This Row],[DESCRIÇÃO]], Materiais_Estoque!$D$5:$D$104, 0)) -> 20917 | D175: Farmácia/Produção | E175: BULA OFICIALFARMA | F175: 2 | G175: Fd C/ 1000 Unid | H175: Farmácia Satélite - Unidade 03 | I175: Assistente Administrativo 04 | J175: 46076 | K175: 46076 | L175: =CONCATENATE(NETWORKDAYS(Consumo_Mensal!$J175, Consumo_Mensal!$K175)-1, " dia") -> 0 dia | M175: =IFERROR(Consumo_Mensal!$F175*VLOOKUP(Consumo_Mensal!$E175,TBEstoque[[DESCRIÇÃO]:[VALOR UNIT. (R$)]],7,0), 0) -> 0
B176: ="PED-" & Consumo_Mensal!$H176 & "-" & TEXT(Consumo_Mensal!$J176, "ddmmaa") -> PED-Farmácia Principal - Unidade 01-230226 | C176: =INDEX(Materiais_Estoque!$B$5:$B$104, MATCH(TBConsumo[[#This Row],[DESCRIÇÃO]], Materiais_Estoque!$D$5:$D$104, 0)) -> 20911 | D176: Farmácia/Produção | E176: ENVELOPE PREMIUN TNT M | F176: 50 | G176: Fd C/ 25 Unid | H176: Farmácia Principal - Unidade 01 | I176: Assistente Administrativo 02 | J176: 46076 | K176: 46076 | L176: =CONCATENATE(NETWORKDAYS(Consumo_Mensal!$J176, Consumo_Mensal!$K176)-1, " dia") -> 0 dia | M176: =IFERROR(Consumo_Mensal!$F176*VLOOKUP(Consumo_Mensal!$E176,TBEstoque[[DESCRIÇÃO]:[VALOR UNIT. (R$)]],7,0), 0) -> 110.4
B177: ="PED-" & Consumo_Mensal!$H177 & "-" & TEXT(Consumo_Mensal!$J177, "ddmmaa") -> PED-Farmácia Principal - Unidade 01-230226 | C177: =INDEX(Materiais_Estoque!$B$5:$B$104, MATCH(TBConsumo[[#This Row],[DESCRIÇÃO]], Materiais_Estoque!$D$5:$D$104, 0)) -> 20912 | D177: Farmácia/Produção | E177: ENVELOPE PREMIUN TNT P | F177: 125 | G177: Fd C/ 25 Unid | H177: Farmácia Principal - Unidade 01 | I177: Assistente Administrativo 02 | J177: 46076 | K177: 46076 | L177: =CONCATENATE(NETWORKDAYS(Consumo_Mensal!$J177, Consumo_Mensal!$K177)-1, " dia") -> 0 dia | M177: =IFERROR(Consumo_Mensal!$F177*VLOOKUP(Consumo_Mensal!$E177,TBEstoque[[DESCRIÇÃO]:[VALOR UNIT. (R$)]],7,0), 0) -> 221.375
B178: ="PED-" & Consumo_Mensal!$H178 & "-" & TEXT(Consumo_Mensal!$J178, "ddmmaa") -> PED-Farmácia Satélite - Unidade 02-260226 | C178: =INDEX(Materiais_Estoque!$B$5:$B$104, MATCH(TBConsumo[[#This Row],[DESCRIÇÃO]], Materiais_Estoque!$D$5:$D$104, 0)) -> 20917 | D178: Farmácia/Produção | E178: BULA OFICIALFARMA | F178: 1 | G178: Fd C/ 1000 Unid | H178: Farmácia Satélite - Unidade 02 | I178: Farmacêutico Pleno 01 | J178: 46079 | K178: 46079 | L178: =CONCATENATE(NETWORKDAYS(Consumo_Mensal!$J178, Consumo_Mensal!$K178)-1, " dia") -> 0 dia | M178: =IFERROR(Consumo_Mensal!$F178*VLOOKUP(Consumo_Mensal!$E178,TBEstoque[[DESCRIÇÃO]:[VALOR UNIT. (R$)]],7,0), 0) -> 0
B179: ="PED-" & Consumo_Mensal!$H179 & "-" & TEXT(Consumo_Mensal!$J179, "ddmmaa") -> PED-Farmácia Satélite - Unidade 03-270226 | C179: 20903 | D179: Farmácia/Produção | E179: SONTARA (UNI) | F179: 3 | G179: Unid | H179: Farmácia Satélite - Unidade 03 | I179: Assistente Administrativo 04 | J179: 46080 | K179: 46083 | L179: =CONCATENATE(NETWORKDAYS(Consumo_Mensal!$J179, Consumo_Mensal!$K179)-1, " dia") -> 1 dia | M179: =IFERROR(Consumo_Mensal!$F179*VLOOKUP(Consumo_Mensal!$E179,TBEstoque[[DESCRIÇÃO]:[VALOR UNIT. (R$)]],7,0), 0) -> 393.3
B180: ="PED-" & Consumo_Mensal!$H180 & "-" & TEXT(Consumo_Mensal!$J180, "ddmmaa") -> PED-Farmácia Satélite - Unidade 03-270226 | C180: 20896 | D180: Farmácia/Produção | E180: LUVA SEM PÓ M LATEX (CX) | F180: 1 | G180: Cx | H180: Farmácia Satélite - Unidade 03 | I180: Assistente Administrativo 04 | J180: 46080 | K180: 46083 | L180: =CONCATENATE(NETWORKDAYS(Consumo_Mensal!$J180, Consumo_Mensal!$K180)-1, " dia") -> 1 dia | M180: =IFERROR(Consumo_Mensal!$F180*VLOOKUP(Consumo_Mensal!$E180,TBEstoque[[DESCRIÇÃO]:[VALOR UNIT. (R$)]],7,0), 0) -> 33.35
B181: ="PED-" & Consumo_Mensal!$H181 & "-" & TEXT(Consumo_Mensal!$J181, "ddmmaa") -> PED-Farmácia Satélite - Unidade 03-270226 | C181: 20897 | D181: Farmácia/Produção | E181: LUVA SEM PÓ P LATEX (CX) | F181: 4 | G181: Cx | H181: Farmácia Satélite - Unidade 03 | I181: Assistente Administrativo 04 | J181: 46080 | K181: 46083 | L181: =CONCATENATE(NETWORKDAYS(Consumo_Mensal!$J181, Consumo_Mensal!$K181)-1, " dia") -> 1 dia | M181: =IFERROR(Consumo_Mensal!$F181*VLOOKUP(Consumo_Mensal!$E181,TBEstoque[[DESCRIÇÃO]:[VALOR UNIT. (R$)]],7,0), 0) -> 133.4
B182: ="PED-" & Consumo_Mensal!$H182 & "-" & TEXT(Consumo_Mensal!$J182, "ddmmaa") -> PED-Farmácia Satélite - Unidade 03-270226 | C182: 20890 | D182: Farmácia/Produção | E182: AVENTAL DESCARTÁVEL PCT C/ 10 UNIDADES | F182: 5 | G182: Pct | H182: Farmácia Satélite - Unidade 03 | I182: Assistente Administrativo 04 | J182: 46080 | K182: 46083 | L182: =CONCATENATE(NETWORKDAYS(Consumo_Mensal!$J182, Consumo_Mensal!$K182)-1, " dia") -> 1 dia | M182: =IFERROR(Consumo_Mensal!$F182*VLOOKUP(Consumo_Mensal!$E182,TBEstoque[[DESCRIÇÃO]:[VALOR UNIT. (R$)]],7,0), 0) -> 137.9425
B183: ="PED-" & Consumo_Mensal!$H183 & "-" & TEXT(Consumo_Mensal!$J183, "ddmmaa") -> PED-Farmácia Satélite - Unidade 03-270226 | C183: =INDEX(Materiais_Estoque!$B$5:$B$104, MATCH(TBConsumo[[#This Row],[DESCRIÇÃO]], Materiais_Estoque!$D$5:$D$104, 0)) -> 20911 | D183: Farmácia/Produção | E183: ENVELOPE PREMIUN TNT M | F183: 125 | G183: Fd C/ 25 Unid | H183: Farmácia Satélite - Unidade 03 | I183: Assistente Administrativo 04 | J183: 46080 | K183: 46083 | L183: =CONCATENATE(NETWORKDAYS(Consumo_Mensal!$J183, Consumo_Mensal!$K183)-1, " dia") -> 1 dia | M183: =IFERROR(Consumo_Mensal!$F183*VLOOKUP(Consumo_Mensal!$E183,TBEstoque[[DESCRIÇÃO]:[VALOR UNIT. (R$)]],7,0), 0) -> 276
B184: ="PED-" & Consumo_Mensal!$H184 & "-" & TEXT(Consumo_Mensal!$J184, "ddmmaa") -> PED-Farmácia Satélite - Unidade 03-270226 | C184: =INDEX(Materiais_Estoque!$B$5:$B$104, MATCH(TBConsumo[[#This Row],[DESCRIÇÃO]], Materiais_Estoque!$D$5:$D$104, 0)) -> 20912 | D184: Farmácia/Produção | E184: ENVELOPE PREMIUN TNT P | F184: 125 | G184: Fd C/ 25 Unid | H184: Farmácia Satélite - Unidade 03 | I184: Assistente Administrativo 04 | J184: 46080 | K184: 46083 | L184: =CONCATENATE(NETWORKDAYS(Consumo_Mensal!$J184, Consumo_Mensal!$K184)-1, " dia") -> 1 dia | M184: =IFERROR(Consumo_Mensal!$F184*VLOOKUP(Consumo_Mensal!$E184,TBEstoque[[DESCRIÇÃO]:[VALOR UNIT. (R$)]],7,0), 0) -> 221.375
B185: ="PED-" & Consumo_Mensal!$H185 & "-" & TEXT(Consumo_Mensal!$J185, "ddmmaa") -> PED-Farmácia Principal - Unidade 01-020326 | C185: =INDEX(Materiais_Estoque!$B$5:$B$104, MATCH(TBConsumo[[#This Row],[DESCRIÇÃO]], Materiais_Estoque!$D$5:$D$104, 0)) -> 20911 | D185: Farmácia/Produção | E185: ENVELOPE PREMIUN TNT M | F185: 75 | G185: Fd C/ 25 Unid | H185: Farmácia Principal - Unidade 01 | I185: Assistente Administrativo 02 | J185: 46083 | K185: 46083 | L185: =CONCATENATE(NETWORKDAYS(Consumo_Mensal!$J185, Consumo_Mensal!$K185)-1, " dia") -> 0 dia | M185: =IFERROR(Consumo_Mensal!$F185*VLOOKUP(Consumo_Mensal!$E185,TBEstoque[[DESCRIÇÃO]:[VALOR UNIT. (R$)]],7,0), 0) -> 165.6
B186: ="PED-" & Consumo_Mensal!$H186 & "-" & TEXT(Consumo_Mensal!$J186, "ddmmaa") -> PED-Farmácia Principal - Unidade 01-020326 | C186: =INDEX(Materiais_Estoque!$B$5:$B$104, MATCH(TBConsumo[[#This Row],[DESCRIÇÃO]], Materiais_Estoque!$D$5:$D$104, 0)) -> 20912 | D186: Farmácia/Produção | E186: ENVELOPE PREMIUN TNT P | F186: 125 | G186: Fd C/ 25 Unid | H186: Farmácia Principal - Unidade 01 | I186: Assistente Administrativo 02 | J186: 46083 | K186: 46083 | L186: =CONCATENATE(NETWORKDAYS(Consumo_Mensal!$J186, Consumo_Mensal!$K186)-1, " dia") -> 0 dia | M186: =IFERROR(Consumo_Mensal!$F186*VLOOKUP(Consumo_Mensal!$E186,TBEstoque[[DESCRIÇÃO]:[VALOR UNIT. (R$)]],7,0), 0) -> 221.375
B187: ="PED-" & Consumo_Mensal!$H187 & "-" & TEXT(Consumo_Mensal!$J187, "ddmmaa") -> PED-Farmácia Principal - Unidade 01-020326 | C187: =INDEX(Materiais_Estoque!$B$5:$B$104, MATCH(TBConsumo[[#This Row],[DESCRIÇÃO]], Materiais_Estoque!$D$5:$D$104, 0)) -> 20913 | D187: Farmácia/Produção | E187: SACOLA G 40X55 + 10CMX0,15MM (SOPLAST) | F187: 100 | G187: Unid | H187: Farmácia Principal - Unidade 01 | I187: Assistente Administrativo 02 | J187: 46083 | K187: 46083 | L187: =CONCATENATE(NETWORKDAYS(Consumo_Mensal!$J187, Consumo_Mensal!$K187)-1, " dia") -> 0 dia | M187: =IFERROR(Consumo_Mensal!$F187*VLOOKUP(Consumo_Mensal!$E187,TBEstoque[[DESCRIÇÃO]:[VALOR UNIT. (R$)]],7,0), 0) -> 132.25
B188: ="PED-" & Consumo_Mensal!$H188 & "-" & TEXT(Consumo_Mensal!$J188, "ddmmaa") -> PED-Farmácia Principal - Unidade 01-020326 | C188: =INDEX(Materiais_Estoque!$B$5:$B$104, MATCH(TBConsumo[[#This Row],[DESCRIÇÃO]], Materiais_Estoque!$D$5:$D$104, 0)) -> 20914 | D188: Farmácia/Produção | E188: SACOLA P 17,5X25 + 3CMX0,13MM (SOPLAST) | F188: 100 | G188: Unid | H188: Farmácia Principal - Unidade 01 | I188: Assistente Administrativo 02 | J188: 46083 | K188: 46083 | L188: =CONCATENATE(NETWORKDAYS(Consumo_Mensal!$J188, Consumo_Mensal!$K188)-1, " dia") -> 0 dia | M188: =IFERROR(Consumo_Mensal!$F188*VLOOKUP(Consumo_Mensal!$E188,TBEstoque[[DESCRIÇÃO]:[VALOR UNIT. (R$)]],7,0), 0) -> 26.45
B189: ="PED-" & Consumo_Mensal!$H189 & "-" & TEXT(Consumo_Mensal!$J189, "ddmmaa") -> PED-Escritório Central - Sede-020326 | C189: 20903 | D189: Farmácia/Produção | E189: SONTARA (UNI) | F189: 1 | G189: Unid | H189: Escritório Central - Sede | I189: Secretária Executiva | J189: 46083 | K189: 46083 | L189: =CONCATENATE(NETWORKDAYS(Consumo_Mensal!$J189, Consumo_Mensal!$K189)-1, " dia") -> 0 dia | M189: =IFERROR(Consumo_Mensal!$F189*VLOOKUP(Consumo_Mensal!$E189,TBEstoque[[DESCRIÇÃO]:[VALOR UNIT. (R$)]],7,0), 0) -> 131.1
B190: ="PED-" & Consumo_Mensal!$H190 & "-" & TEXT(Consumo_Mensal!$J190, "ddmmaa") -> PED-Farmácia Principal - Unidade 01-030326 | C190: 20901 | D190: Farmácia/Produção | E190: PROPÉ (PCT C/100) | F190: 10 | G190: Pct | H190: Farmácia Principal - Unidade 01 | I190: Gestor de Inventário | J190: 46084 | K190: 46085 | L190: =CONCATENATE(NETWORKDAYS(Consumo_Mensal!$J190, Consumo_Mensal!$K190)-1, " dia") -> 1 dia | M190: =IFERROR(Consumo_Mensal!$F190*VLOOKUP(Consumo_Mensal!$E190,TBEstoque[[DESCRIÇÃO]:[VALOR UNIT. (R$)]],7,0), 0) -> 138
B191: ="PED-" & Consumo_Mensal!$H191 & "-" & TEXT(Consumo_Mensal!$J191, "ddmmaa") -> PED-Farmácia Principal - Unidade 01-030326 | C191: 20897 | D191: Farmácia/Produção | E191: LUVA SEM PÓ P LATEX (CX) | F191: 5 | G191: Cx | H191: Farmácia Principal - Unidade 01 | I191: Gestor de Inventário | J191: 46084 | K191: 46085 | L191: =CONCATENATE(NETWORKDAYS(Consumo_Mensal!$J191, Consumo_Mensal!$K191)-1, " dia") -> 1 dia | M191: =IFERROR(Consumo_Mensal!$F191*VLOOKUP(Consumo_Mensal!$E191,TBEstoque[[DESCRIÇÃO]:[VALOR UNIT. (R$)]],7,0), 0) -> 166.75
B192: ="PED-" & Consumo_Mensal!$H192 & "-" & TEXT(Consumo_Mensal!$J192, "ddmmaa") -> PED-Farmácia Principal - Unidade 01-030326 | C192: 20896 | D192: Farmácia/Produção | E192: LUVA SEM PÓ M LATEX (CX) | F192: 5 | G192: Cx | H192: Farmácia Principal - Unidade 01 | I192: Gestor de Inventário | J192: 46084 | K192: 46085 | L192: =CONCATENATE(NETWORKDAYS(Consumo_Mensal!$J192, Consumo_Mensal!$K192)-1, " dia") -> 1 dia | M192: =IFERROR(Consumo_Mensal!$F192*VLOOKUP(Consumo_Mensal!$E192,TBEstoque[[DESCRIÇÃO]:[VALOR UNIT. (R$)]],7,0), 0) -> 166.75
B193: ="PED-" & Consumo_Mensal!$H193 & "-" & TEXT(Consumo_Mensal!$J193, "ddmmaa") -> PED-Farmácia Principal - Unidade 01-030326 | C193: 20984 | D193: Farmácia/Produção | E193: PAPEL MULTIUSO INTERFOLHADO DEMARCARE NEVE | F193: 20 | G193: Pct | H193: Farmácia Principal - Unidade 01 | I193: Gestor de Inventário | J193: 46084 | K193: 46085 | L193: =CONCATENATE(NETWORKDAYS(Consumo_Mensal!$J193, Consumo_Mensal!$K193)-1, " dia") -> 1 dia | M193: =IFERROR(Consumo_Mensal!$F193*VLOOKUP(Consumo_Mensal!$E193,TBEstoque[[DESCRIÇÃO]:[VALOR UNIT. (R$)]],7,0), 0) -> 193.89
B194: ="PED-" & Consumo_Mensal!$H194 & "-" & TEXT(Consumo_Mensal!$J194, "ddmmaa") -> PED-Farmácia Satélite - Unidade 05-030326 | C194: 20894 | D194: Farmácia/Produção | E194: LUVA COM PÓ PP LATEX (CX) | F194: 10 | G194: Cx | H194: Farmácia Satélite - Unidade 05 | I194: Assistente Administrativo 03 | J194: 46084 | K194: 46085 | L194: =CONCATENATE(NETWORKDAYS(Consumo_Mensal!$J194, Consumo_Mensal!$K194)-1, " dia") -> 1 dia | M194: =IFERROR(Consumo_Mensal!$F194*VLOOKUP(Consumo_Mensal!$E194,TBEstoque[[DESCRIÇÃO]:[VALOR UNIT. (R$)]],7,0), 0) -> 333.5
B195: ="PED-" & Consumo_Mensal!$H195 & "-" & TEXT(Consumo_Mensal!$J195, "ddmmaa") -> PED-Farmácia Satélite - Unidade 05-030326 | C195: 20903 | D195: Farmácia/Produção | E195: SONTARA (UNI) | F195: 4 | G195: Unid | H195: Farmácia Satélite - Unidade 05 | I195: Assistente Administrativo 03 | J195: 46084 | K195: 46085 | L195: =CONCATENATE(NETWORKDAYS(Consumo_Mensal!$J195, Consumo_Mensal!$K195)-1, " dia") -> 1 dia | M195: =IFERROR(Consumo_Mensal!$F195*VLOOKUP(Consumo_Mensal!$E195,TBEstoque[[DESCRIÇÃO]:[VALOR UNIT. (R$)]],7,0), 0) -> 524.4
B196: ="PED-" & Consumo_Mensal!$H196 & "-" & TEXT(Consumo_Mensal!$J196, "ddmmaa") -> PED-Planta Industrial - Suprimentos-050326 | C196: 20894 | D196: Farmácia/Produção | E196: LUVA COM PÓ PP LATEX (CX) | F196: 20 | G196: Cx | H196: Planta Industrial - Suprimentos | I196: Almoxarife Jr | J196: 46086 | K196: 46087 | L196: =CONCATENATE(NETWORKDAYS(Consumo_Mensal!$J196, Consumo_Mensal!$K196)-1, " dia") -> 1 dia | M196: =IFERROR(Consumo_Mensal!$F196*VLOOKUP(Consumo_Mensal!$E196,TBEstoque[[DESCRIÇÃO]:[VALOR UNIT. (R$)]],7,0), 0) -> 667
B197: ="PED-" & Consumo_Mensal!$H197 & "-" & TEXT(Consumo_Mensal!$J197, "ddmmaa") -> PED-Planta Industrial - Suprimentos-050326 | C197: 20893 | D197: Farmácia/Produção | E197: LUVA COM PÓ P LATEX (CX) | F197: 40 | G197: Cx | H197: Planta Industrial - Suprimentos | I197: Almoxarife Jr | J197: 46086 | K197: 46087 | L197: =CONCATENATE(NETWORKDAYS(Consumo_Mensal!$J197, Consumo_Mensal!$K197)-1, " dia") -> 1 dia | M197: =IFERROR(Consumo_Mensal!$F197*VLOOKUP(Consumo_Mensal!$E197,TBEstoque[[DESCRIÇÃO]:[VALOR UNIT. (R$)]],7,0), 0) -> 1334
B198: ="PED-" & Consumo_Mensal!$H198 & "-" & TEXT(Consumo_Mensal!$J198, "ddmmaa") -> PED-Planta Industrial - Suprimentos-050326 | C198: 20892 | D198: Farmácia/Produção | E198: Luva Com Pó M Latex (Cx) | F198: 30 | G198: Cx | H198: Planta Industrial - Suprimentos | I198: Almoxarife Jr | J198: 46086 | K198: 46087 | L198: =CONCATENATE(NETWORKDAYS(Consumo_Mensal!$J198, Consumo_Mensal!$K198)-1, " dia") -> 1 dia | M198: =IFERROR(Consumo_Mensal!$F198*VLOOKUP(Consumo_Mensal!$E198,TBEstoque[[DESCRIÇÃO]:[VALOR UNIT. (R$)]],7,0), 0) -> 1000.5
B199: ="PED-" & Consumo_Mensal!$H199 & "-" & TEXT(Consumo_Mensal!$J199, "ddmmaa") -> PED-Farmácia Satélite - Unidade 03-050326 | C199: 20902 | D199: Farmácia/Produção | E199: MÁSCARA TRIPLA DESCARTÁVEL (CAIXA 50 UNI) | F199: 10 | G199: Pct | H199: Farmácia Satélite - Unidade 03 | I199: Assistente Administrativo 04 | J199: 46086 | K199: 46087 | L199: =CONCATENATE(NETWORKDAYS(Consumo_Mensal!$J199, Consumo_Mensal!$K199)-1, " dia") -> 1 dia | M199: =IFERROR(Consumo_Mensal!$F199*VLOOKUP(Consumo_Mensal!$E199,TBEstoque[[DESCRIÇÃO]:[VALOR UNIT. (R$)]],7,0), 0) -> 333.5
B200: ="PED-" & Consumo_Mensal!$H200 & "-" & TEXT(Consumo_Mensal!$J200, "ddmmaa") -> PED-Farmácia Satélite - Unidade 03-050326 | C200: 20898 | D200: Farmácia/Produção | E200: LUVA SEM PÓ PP LATEX (CX) | F200: 10 | G200: Cx | H200: Farmácia Satélite - Unidade 03 | I200: Assistente Administrativo 04 | J200: 46086 | K200: 46087 | L200: =CONCATENATE(NETWORKDAYS(Consumo_Mensal!$J200, Consumo_Mensal!$K200)-1, " dia") -> 1 dia | M200: =IFERROR(Consumo_Mensal!$F200*VLOOKUP(Consumo_Mensal!$E200,TBEstoque[[DESCRIÇÃO]:[VALOR UNIT. (R$)]],7,0), 0) -> 333.5
... B203: ="PED-" & Consumo_Mensal!$H203 & "-" & TEXT(Consumo_Mensal!$J203, "ddmmaa") -> PED-Farmácia Principal - Unidade 01-090326 | C203: 20897 | D203: Farmácia/Produção | E203: LUVA SEM PÓ P LATEX (CX) | F203: 6 | G203: Cx | H203: Farmácia Principal - Unidade 01 | I203: Gestor de Inventário | J203: 46090 | K203: 46090 | L203: =CONCATENATE(NETWORKDAYS(Consumo_Mensal!$J203, Consumo_Mensal!$K203)-1, " dia") -> 0 dia | M203: =IFERROR(Consumo_Mensal!$F203*VLOOKUP(Consumo_Mensal!$E203,TBEstoque[[DESCRIÇÃO]:[VALOR UNIT. (R$)]],7,0), 0) -> 200.1
B204: ="PED-" & Consumo_Mensal!$H204 & "-" & TEXT(Consumo_Mensal!$J204, "ddmmaa") -> PED-Farmácia Principal - Unidade 01-090326 | C204: =INDEX(Materiais_Estoque!$B$5:$B$104, MATCH(TBConsumo[[#This Row],[DESCRIÇÃO]], Materiais_Estoque!$D$5:$D$104, 0)) -> 20918 | D204: Farmácia/Produção | E204: FRASCO DESCARTÁVEL Y | F204: 1 | G204: Cx | H204: Farmácia Principal - Unidade 01 | I204: Gestor de Inventário | J204: 46090 | K204: 46090 | L204: =CONCATENATE(NETWORKDAYS(Consumo_Mensal!$J204, Consumo_Mensal!$K204)-1, " dia") -> 0 dia | M204: =IFERROR(Consumo_Mensal!$F204*VLOOKUP(Consumo_Mensal!$E204,TBEstoque[[DESCRIÇÃO]:[VALOR UNIT. (R$)]],7,0), 0) -> 0
B205: ="PED-" & Consumo_Mensal!$H205 & "-" & TEXT(Consumo_Mensal!$J205, "ddmmaa") -> PED-Farmácia Principal - Unidade 01-090326 | C205: 20984 | D205: Farmácia/Produção | E205: PAPEL MULTIUSO INTERFOLHADO DEMARCARE NEVE | F205: 20 | G205: Pct | H205: Farmácia Principal - Unidade 01 | I205: Gestor de Inventário | J205: 46090 | K205: 46090 | L205: =CONCATENATE(NETWORKDAYS(Consumo_Mensal!$J205, Consumo_Mensal!$K205)-1, " dia") -> 0 dia | M205: =IFERROR(Consumo_Mensal!$F205*VLOOKUP(Consumo_Mensal!$E205,TBEstoque[[DESCRIÇÃO]:[VALOR UNIT. (R$)]],7,0), 0) -> 193.89
B206: ="PED-" & Consumo_Mensal!$H206 & "-" & TEXT(Consumo_Mensal!$J206, "ddmmaa") -> PED-Farmácia Principal - Unidade 01-090326 | C206: 20890 | D206: Farmácia/Produção | E206: AVENTAL DESCARTÁVEL PCT C/ 10 UNIDADES | F206: 8 | G206: Pct | H206: Farmácia Principal - Unidade 01 | I206: Gestor de Inventário | J206: 46090 | K206: 46090 | L206: =CONCATENATE(NETWORKDAYS(Consumo_Mensal!$J206, Consumo_Mensal!$K206)-1, " dia") -> 0 dia | M206: =IFERROR(Consumo_Mensal!$F206*VLOOKUP(Consumo_Mensal!$E206,TBEstoque[[DESCRIÇÃO]:[VALOR UNIT. (R$)]],7,0), 0) -> 220.708
B207: ="PED-" & Consumo_Mensal!$H207 & "-" & TEXT(Consumo_Mensal!$J207, "ddmmaa") -> PED-Farmácia Principal - Unidade 01-090326 | C207: 20904 | D207: Farmácia/Produção | E207: TOUCA SANFONADA BRANCO DESCARTÁVEL (PCT C/100) | F207: 8 | G207: Pct | H207: Farmácia Principal - Unidade 01 | I207: Gestor de Inventário | J207: 46090 | K207: 46090 | L207: =CONCATENATE(NETWORKDAYS(Consumo_Mensal!$J207, Consumo_Mensal!$K207)-1, " dia") -> 0 dia | M207: =IFERROR(Consumo_Mensal!$F207*VLOOKUP(Consumo_Mensal!$E207,TBEstoque[[DESCRIÇÃO]:[VALOR UNIT. (R$)]],7,0), 0) -> 82.616
B208: ="PED-" & Consumo_Mensal!$H208 & "-" & TEXT(Consumo_Mensal!$J208, "ddmmaa") -> PED-Farmácia Principal - Unidade 01-090326 | C208: =INDEX(Materiais_Estoque!$B$5:$B$104, MATCH(TBConsumo[[#This Row],[DESCRIÇÃO]], Materiais_Estoque!$D$5:$D$104, 0)) -> 20912 | D208: Farmácia/Produção | E208: ENVELOPE PREMIUN TNT P | F208: 150 | G208: Fd C/ 25 Unid | H208: Farmácia Principal - Unidade 01 | I208: Assistente Administrativo 02 | J208: 46090 | K208: 46090 | L208: =CONCATENATE(NETWORKDAYS(Consumo_Mensal!$J208, Consumo_Mensal!$K208)-1, " dia") -> 0 dia | M208: =IFERROR(Consumo_Mensal!$F208*VLOOKUP(Consumo_Mensal!$E208,TBEstoque[[DESCRIÇÃO]:[VALOR UNIT. (R$)]],7,0), 0) -> 265.65
B209: ="PED-" & Consumo_Mensal!$H209 & "-" & TEXT(Consumo_Mensal!$J209, "ddmmaa") -> PED-Farmácia Principal - Unidade 01-090326 | C209: =INDEX(Materiais_Estoque!$B$5:$B$104, MATCH(TBConsumo[[#This Row],[DESCRIÇÃO]], Materiais_Estoque!$D$5:$D$104, 0)) -> 20913 | D209: Farmácia/Produção | E209: SACOLA G 40X55 + 10CMX0,15MM (SOPLAST) | F209: 100 | G209: Unid | H209: Farmácia Principal - Unidade 01 | I209: Assistente Administrativo 02 | J209: 46090 | K209: 46090 | L209: =CONCATENATE(NETWORKDAYS(Consumo_Mensal!$J209, Consumo_Mensal!$K209)-1, " dia") -> 0 dia | M209: =IFERROR(Consumo_Mensal!$F209*VLOOKUP(Consumo_Mensal!$E209,TBEstoque[[DESCRIÇÃO]:[VALOR UNIT. (R$)]],7,0), 0) -> 132.25
B210: ="PED-" & Consumo_Mensal!$H210 & "-" & TEXT(Consumo_Mensal!$J210, "ddmmaa") -> PED-Centro de Distribuição - Áragon-090326 | C210: 20892 | D210: Farmácia/Produção | E210: Luva Com Pó M Latex (Cx) | F210: 1 | G210: Cx | H210: Centro de Distribuição - Áragon | I210: Líder de Equipe 02 | J210: 46090 | K210: 46090 | L210: =CONCATENATE(NETWORKDAYS(Consumo_Mensal!$J210, Consumo_Mensal!$K210)-1, " dia") -> 0 dia | M210: =IFERROR(Consumo_Mensal!$F210*VLOOKUP(Consumo_Mensal!$E210,TBEstoque[[DESCRIÇÃO]:[VALOR UNIT. (R$)]],7,0), 0) -> 33.35
B211: ="PED-" & Consumo_Mensal!$H211 & "-" & TEXT(Consumo_Mensal!$J211, "ddmmaa") -> PED-Farmácia Satélite - Unidade 03-110326 | C211: 20903 | D211: Farmácia/Produção | E211: SONTARA (UNI) | F211: 4 | G211: Unid | H211: Farmácia Satélite - Unidade 03 | I211: Assistente Administrativo 04 | J211: 46092 | K211: 46093 | L211: =CONCATENATE(NETWORKDAYS(Consumo_Mensal!$J211, Consumo_Mensal!$K211)-1, " dia") -> 1 dia | M211: =IFERROR(Consumo_Mensal!$F211*VLOOKUP(Consumo_Mensal!$E211,TBEstoque[[DESCRIÇÃO]:[VALOR UNIT. (R$)]],7,0), 0) -> 524.4
B212: ="PED-" & Consumo_Mensal!$H212 & "-" & TEXT(Consumo_Mensal!$J212, "ddmmaa") -> PED-Farmácia Satélite - Unidade 03-110326 | C212: 20901 | D212: Farmácia/Produção | E212: PROPÉ (PCT C/100) | F212: 6 | G212: Pct | H212: Farmácia Satélite - Unidade 03 | I212: Assistente Administrativo 04 | J212: 46092 | K212: 46093 | L212: =CONCATENATE(NETWORKDAYS(Consumo_Mensal!$J212, Consumo_Mensal!$K212)-1, " dia") -> 1 dia | M212: =IFERROR(Consumo_Mensal!$F212*VLOOKUP(Consumo_Mensal!$E212,TBEstoque[[DESCRIÇÃO]:[VALOR UNIT. (R$)]],7,0), 0) -> 82.8
B213: ="PED-" & Consumo_Mensal!$H213 & "-" & TEXT(Consumo_Mensal!$J213, "ddmmaa") -> PED-Planta Industrial - Suprimentos-120326 | C213: 20902 | D213: Farmácia/Produção | E213: MÁSCARA TRIPLA DESCARTÁVEL (CAIXA 50 UNI) | F213: 50 | G213: Pct | H213: Planta Industrial - Suprimentos | I213: Almoxarife Jr | J213: 46093 | K213: 46094 | L213: =CONCATENATE(NETWORKDAYS(Consumo_Mensal!$J213, Consumo_Mensal!$K213)-1, " dia") -> 1 dia | M213: =IFERROR(Consumo_Mensal!$F213*VLOOKUP(Consumo_Mensal!$E213,TBEstoque[[DESCRIÇÃO]:[VALOR UNIT. (R$)]],7,0), 0) -> 1667.5
B214: ="PED-" & Consumo_Mensal!$H214 & "-" & TEXT(Consumo_Mensal!$J214, "ddmmaa") -> PED-Farmácia Satélite - Unidade 03-120326 | C214: =INDEX(Materiais_Estoque!$B$5:$B$104, MATCH(TBConsumo[[#This Row],[DESCRIÇÃO]], Materiais_Estoque!$D$5:$D$104, 0)) -> 20918 | D214: Farmácia/Produção | E214: FRASCO DESCARTÁVEL Y | F214: 1 | G214: Cx | H214: Farmácia Satélite - Unidade 03 | I214: Assistente Administrativo 04 | J214: 46093 | K214: 46094 | L214: =CONCATENATE(NETWORKDAYS(Consumo_Mensal!$J214, Consumo_Mensal!$K214)-1, " dia") -> 1 dia | M214: =IFERROR(Consumo_Mensal!$F214*VLOOKUP(Consumo_Mensal!$E214,TBEstoque[[DESCRIÇÃO]:[VALOR UNIT. (R$)]],7,0), 0) -> 0
B215: ="PED-" & Consumo_Mensal!$H215 & "-" & TEXT(Consumo_Mensal!$J215, "ddmmaa") -> PED-Farmácia Satélite - Unidade 03-120326 | C215: 20904 | D215: Farmácia/Produção | E215: TOUCA SANFONADA BRANCO DESCARTÁVEL (PCT C/100) | F215: 6 | G215: Pct | H215: Farmácia Satélite - Unidade 03 | I215: Assistente Administrativo 04 | J215: 46093 | K215: 46094 | L215: =CONCATENATE(NETWORKDAYS(Consumo_Mensal!$J215, Consumo_Mensal!$K215)-1, " dia") -> 1 dia | M215: =IFERROR(Consumo_Mensal!$F215*VLOOKUP(Consumo_Mensal!$E215,TBEstoque[[DESCRIÇÃO]:[VALOR UNIT. (R$)]],7,0), 0) -> 61.962
B216: ="PED-" & Consumo_Mensal!$H216 & "-" & TEXT(Consumo_Mensal!$J216, "ddmmaa") -> PED-Farmácia Satélite - Unidade 03-120326 | C216: 20984 | D216: Farmácia/Produção | E216: PAPEL MULTIUSO INTERFOLHADO DEMARCARE NEVE | F216: 10 | G216: Pct | H216: Farmácia Satélite - Unidade 03 | I216: Assistente Administrativo 04 | J216: 46093 | K216: 46094 | L216: =CONCATENATE(NETWORKDAYS(Consumo_Mensal!$J216, Consumo_Mensal!$K216)-1, " dia") -> 1 dia | M216: =IFERROR(Consumo_Mensal!$F216*VLOOKUP(Consumo_Mensal!$E216,TBEstoque[[DESCRIÇÃO]:[VALOR UNIT. (R$)]],7,0), 0) -> 96.945
B217: ="PED-" & Consumo_Mensal!$H217 & "-" & TEXT(Consumo_Mensal!$J217, "ddmmaa") -> PED-Escritório Apoio - Gestão-130326 | C217: 20896 | D217: Farmácia/Produção | E217: LUVA SEM PÓ M LATEX (CX) | F217: 2 | G217: Cx | H217: Escritório Apoio - Gestão | I217: Analista Financeiro | J217: 46094 | K217: 46097 | L217: =CONCATENATE(NETWORKDAYS(Consumo_Mensal!$J217, Consumo_Mensal!$K217)-1, " dia") -> 1 dia | M217: =IFERROR(Consumo_Mensal!$F217*VLOOKUP(Consumo_Mensal!$E217,TBEstoque[[DESCRIÇÃO]:[VALOR UNIT. (R$)]],7,0), 0) -> 66.7
B218: ="PED-" & Consumo_Mensal!$H218 & "-" & TEXT(Consumo_Mensal!$J218, "ddmmaa") -> PED-Farmácia Principal - Unidade 01-100226 | C218: 20811 | D218: Geral | E218: FOLHA DE SULFITE A5 PACOTE | F218: 12 | G218: Pct | H218: Farmácia Principal - Unidade 01 | I218: Gestor de Inventário | J218: 46063 | K218: 46064 | L218: =CONCATENATE(NETWORKDAYS(Consumo_Mensal!$J218, Consumo_Mensal!$K218)-1, " dia") -> 1 dia | M218: =IFERROR(Consumo_Mensal!$F218*VLOOKUP(Consumo_Mensal!$E218,TBEstoque[[DESCRIÇÃO]:[VALOR UNIT. (R$)]],7,0), 0) -> 171.81
...

Sheet Suprimentos_LeadTime
B4: SKU | C4: CATEGÓRIA | D4: DESCRIÇÃO | E4: UNID. MEDIDA | F4: ESTOQUE ATUAL | G4: MÉDIA CONSUMO | H4: STATUS COMPRA | I4: FATOR EMBALAGEM | J4: FATOR MEDIDA | K4: SUGESTÃO QTDE | L4: CUSTO PEDIDO (R$) | M4: DATA SOLICITADA | N4: PRAZO FORNECEDOR (DIAS) | O4: LEAD TIME ALVO | P4: DATA ENTREGA (REAL) | Q4: FORNECEDOR
B5: =TBEstoque[[#This Row],[SKU]] -> 20814 | C5: =IF(TBEstoque[[#This Row],[SKU]]=TBSuprimentos[[#This Row],[SKU]],TBEstoque[[#This Row],[CATEGÓRIA]]," ") -> Copa | D5: =IF(TBSuprimentos[[#This Row],[SKU]]=TBEstoque[[#This Row],[SKU]],TBEstoque[[#This Row],[DESCRIÇÃO]]," ") -> AÇÚCAR (UNID) PACOTE 1 KG | E5: =IF(TBSuprimentos[[#This Row],[SKU]]=TBEstoque[[#This Row],[SKU]],TBEstoque[[#This Row],[UNID. MEDIDA]]," ") -> Pct | F5: =_xlfn.XLOOKUP(TBSuprimentos[[#This Row],[SKU]], TBEstoque[SKU], TBEstoque[ESTOQUE ATUAL], 0) - SUMIF(TBConsumo[SKU], TBSuprimentos[[#This Row],[SKU]], TBConsumo[QTDE SOLICITADA]) -> 42 | G5: =VLOOKUP(TBSuprimentos[[#This Row],[DESCRIÇÃO]],TBEstoque[[DESCRIÇÃO]:[CONSUMO MÉDIO MENSAL]],4,0) -> 50 | H5: =IF(F5 <= (G5/30)*20, "RUPTURA", IF(F5 < G5, "COMPRA IMEDIATA", IF(F5 > G5*2, "EXCESSO", "SAUDÁVEL"))) -> COMPRA IMEDIATA | I5: 10 | J5: Fardo | K5: =IF(OR(H5="COMPRA IMEDIATA", H5="RUPTURA"), IF(ROUNDUP((MAX(IF(OR(C5="Copa",C5="Limpeza"), F5*2, F5*4), G5+F5) - F5) / I5, 0)<=0, "---", ROUNDUP((MAX(IF(OR(C5="Copa",C5="Limpeza"), F5*2, F5*4), G5+F5) - F5) / I5, 0) * I5 & " " & E5), "---") -> 50 Pct | L5: =IF(OR(H5="COMPRA IMEDIATA", H5="RUPTURA"), IF(K5="---", 0, _xlfn.XLOOKUP(B5, TBEstoque[SKU], TBEstoque[VALOR UNIT. (R$)]) * VALUE(LEFT(K5, SEARCH(" ", K5)-1))), "---") -> 340.975 | M5: 46097 | N5: 15 | O5: =IF(OR(H5="COMPRA IMEDIATA", H5="RUPTURA"), WORKDAY(M5,N5,Feriados!$A$3:$A$19),"---") -> 46119 | Q5: =IFERROR(_xlfn.LET(_xlpm.f, _xlfn.XLOOKUP(D5, TBEstoque[DESCRIÇÃO], TBEstoque[FORNECEDOR], "---"), IF(_xlpm.f=0, "---", _xlpm.f)), "---") -> FORNECEDOR 01
B6: =TBEstoque[[#This Row],[SKU]] -> 20815 | C6: =IF(TBEstoque[[#This Row],[SKU]]=TBSuprimentos[[#This Row],[SKU]],TBEstoque[[#This Row],[CATEGÓRIA]]," ") -> Copa | D6: =IF(TBSuprimentos[[#This Row],[SKU]]=TBEstoque[[#This Row],[SKU]],TBEstoque[[#This Row],[DESCRIÇÃO]]," ") -> CAFÉ EM GRÃO MÁQUINA (UNID) | E6: =IF(TBSuprimentos[[#This Row],[SKU]]=TBEstoque[[#This Row],[SKU]],TBEstoque[[#This Row],[UNID. MEDIDA]]," ") -> Pct | F6: =_xlfn.XLOOKUP(TBSuprimentos[[#This Row],[SKU]], TBEstoque[SKU], TBEstoque[ESTOQUE ATUAL], 0) - SUMIF(TBConsumo[SKU], TBSuprimentos[[#This Row],[SKU]], TBConsumo[QTDE SOLICITADA]) -> 146 | G6: =VLOOKUP(TBSuprimentos[[#This Row],[DESCRIÇÃO]],TBEstoque[[DESCRIÇÃO]:[CONSUMO MÉDIO MENSAL]],4,0) -> 100 | H6: =IF(F6 <= (G6/30)*20, "RUPTURA", IF(F6 < G6, "COMPRA IMEDIATA", IF(F6 > G6*2, "EXCESSO", "SAUDÁVEL"))) -> SAUDÁVEL | I6: 5 | J6: Fardo | K6: =IF(OR(H6="COMPRA IMEDIATA", H6="RUPTURA"), IF(ROUNDUP((MAX(IF(OR(C6="Copa",C6="Limpeza"), F6*2, F6*4), G6+F6) - F6) / I6, 0)<=0, "---", ROUNDUP((MAX(IF(OR(C6="Copa",C6="Limpeza"), F6*2, F6*4), G6+F6) - F6) / I6, 0) * I6 & " " & E6), "---") -> --- | L6: =IF(OR(H6="COMPRA IMEDIATA", H6="RUPTURA"), IF(K6="---", 0, _xlfn.XLOOKUP(B6, TBEstoque[SKU], TBEstoque[VALOR UNIT. (R$)]) * VALUE(LEFT(K6, SEARCH(" ", K6)-1))), "---") -> --- | M6: 46097 | N6: 15 | O6: =IF(OR(H6="COMPRA IMEDIATA", H6="RUPTURA"), WORKDAY(M6,N6,Feriados!$A$3:$A$19),"---") -> --- | Q6: =IFERROR(_xlfn.LET(_xlpm.f, _xlfn.XLOOKUP(D6, TBEstoque[DESCRIÇÃO], TBEstoque[FORNECEDOR], "---"), IF(_xlpm.f=0, "---", _xlpm.f)), "---") -> FORNECEDOR 02
B7: =TBEstoque[[#This Row],[SKU]] -> 20816 | C7: =IF(TBEstoque[[#This Row],[SKU]]=TBSuprimentos[[#This Row],[SKU]],TBEstoque[[#This Row],[CATEGÓRIA]]," ") -> Copa | D7: =IF(TBSuprimentos[[#This Row],[SKU]]=TBEstoque[[#This Row],[SKU]],TBEstoque[[#This Row],[DESCRIÇÃO]]," ") -> CAFÉ EM PÓ (UNID) PACOTE 500 GRAMAS | E7: =IF(TBSuprimentos[[#This Row],[SKU]]=TBEstoque[[#This Row],[SKU]],TBEstoque[[#This Row],[UNID. MEDIDA]]," ") -> Pct | F7: =_xlfn.XLOOKUP(TBSuprimentos[[#This Row],[SKU]], TBEstoque[SKU], TBEstoque[ESTOQUE ATUAL], 0) - SUMIF(TBConsumo[SKU], TBSuprimentos[[#This Row],[SKU]], TBConsumo[QTDE SOLICITADA]) -> 38 | G7: =VLOOKUP(TBSuprimentos[[#This Row],[DESCRIÇÃO]],TBEstoque[[DESCRIÇÃO]:[CONSUMO MÉDIO MENSAL]],4,0) -> 40 | H7: =IF(F7 <= (G7/30)*20, "RUPTURA", IF(F7 < G7, "COMPRA IMEDIATA", IF(F7 > G7*2, "EXCESSO", "SAUDÁVEL"))) -> COMPRA IMEDIATA | I7: 20 | J7: Caixa | K7: =IF(OR(H7="COMPRA IMEDIATA", H7="RUPTURA"), IF(ROUNDUP((MAX(IF(OR(C7="Copa",C7="Limpeza"), F7*2, F7*4), G7+F7) - F7) / I7, 0)<=0, "---", ROUNDUP((MAX(IF(OR(C7="Copa",C7="Limpeza"), F7*2, F7*4), G7+F7) - F7) / I7, 0) * I7 & " " & E7), "---") -> 40 Pct | L7: =IF(OR(H7="COMPRA IMEDIATA", H7="RUPTURA"), IF(K7="---", 0, _xlfn.XLOOKUP(B7, TBEstoque[SKU], TBEstoque[VALOR UNIT. (R$)]) * VALUE(LEFT(K7, SEARCH(" ", K7)-1))), "---") -> 2065.4 | M7: 46097 | N7: 15 | O7: =IF(OR(H7="COMPRA IMEDIATA", H7="RUPTURA"), WORKDAY(M7,N7,Feriados!$A$3:$A$19),"---") -> 46119 | Q7: =IFERROR(_xlfn.LET(_xlpm.f, _xlfn.XLOOKUP(D7, TBEstoque[DESCRIÇÃO], TBEstoque[FORNECEDOR], "---"), IF(_xlpm.f=0, "---", _xlpm.f)), "---") -> FORNECEDOR 03
B8: =TBEstoque[[#This Row],[SKU]] -> 20817 | C8: =IF(TBEstoque[[#This Row],[SKU]]=TBSuprimentos[[#This Row],[SKU]],TBEstoque[[#This Row],[CATEGÓRIA]]," ") -> Copa | D8: =IF(TBSuprimentos[[#This Row],[SKU]]=TBEstoque[[#This Row],[SKU]],TBEstoque[[#This Row],[DESCRIÇÃO]]," ") -> CHOCOLATE EM PÓ 1KG (UNID) | E8: =IF(TBSuprimentos[[#This Row],[SKU]]=TBEstoque[[#This Row],[SKU]],TBEstoque[[#This Row],[UNID. MEDIDA]]," ") -> Pct | F8: =_xlfn.XLOOKUP(TBSuprimentos[[#This Row],[SKU]], TBEstoque[SKU], TBEstoque[ESTOQUE ATUAL], 0) - SUMIF(TBConsumo[SKU], TBSuprimentos[[#This Row],[SKU]], TBConsumo[QTDE SOLICITADA]) -> 121 | G8: =VLOOKUP(TBSuprimentos[[#This Row],[DESCRIÇÃO]],TBEstoque[[DESCRIÇÃO]:[CONSUMO MÉDIO MENSAL]],4,0) -> 120 | H8: =IF(F8 <= (G8/30)*20, "RUPTURA", IF(F8 < G8, "COMPRA IMEDIATA", IF(F8 > G8*2, "EXCESSO", "SAUDÁVEL"))) -> SAUDÁVEL | I8: 10 | J8: Caixa | K8: =IF(OR(H8="COMPRA IMEDIATA", H8="RUPTURA"), IF(ROUNDUP((MAX(IF(OR(C8="Copa",C8="Limpeza"), F8*2, F8*4), G8+F8) - F8) / I8, 0)<=0, "---", ROUNDUP((MAX(IF(OR(C8="Copa",C8="Limpeza"), F8*2, F8*4), G8+F8) - F8) / I8, 0) * I8 & " " & E8), "---") -> --- | L8: =IF(OR(H8="COMPRA IMEDIATA", H8="RUPTURA"), IF(K8="---", 0, _xlfn.XLOOKUP(B8, TBEstoque[SKU], TBEstoque[VALOR UNIT. (R$)]) * VALUE(LEFT(K8, SEARCH(" ", K8)-1))), "---") -> --- | M8: 46097 | N8: 15 | O8: =IF(OR(H8="COMPRA IMEDIATA", H8="RUPTURA"), WORKDAY(M8,N8,Feriados!$A$3:$A$19),"---") -> --- | Q8: =IFERROR(_xlfn.LET(_xlpm.f, _xlfn.XLOOKUP(D8, TBEstoque[DESCRIÇÃO], TBEstoque[FORNECEDOR], "---"), IF(_xlpm.f=0, "---", _xlpm.f)), "---") -> FORNECEDOR 04
B9: =TBEstoque[[#This Row],[SKU]] -> 20818 | C9: =IF(TBEstoque[[#This Row],[SKU]]=TBSuprimentos[[#This Row],[SKU]],TBEstoque[[#This Row],[CATEGÓRIA]]," ") -> Copa | D9: =IF(TBSuprimentos[[#This Row],[SKU]]=TBEstoque[[#This Row],[SKU]],TBEstoque[[#This Row],[DESCRIÇÃO]]," ") -> COPO DESCARTÁVEL 160ML (PCT) | E9: =IF(TBSuprimentos[[#This Row],[SKU]]=TBEstoque[[#This Row],[SKU]],TBEstoque[[#This Row],[UNID. MEDIDA]]," ") -> Pct | F9: =_xlfn.XLOOKUP(TBSuprimentos[[#This Row],[SKU]], TBEstoque[SKU], TBEstoque[ESTOQUE ATUAL], 0) - SUMIF(TBConsumo[SKU], TBSuprimentos[[#This Row],[SKU]], TBConsumo[QTDE SOLICITADA]) -> 38 | G9: =VLOOKUP(TBSuprimentos[[#This Row],[DESCRIÇÃO]],TBEstoque[[DESCRIÇÃO]:[CONSUMO MÉDIO MENSAL]],4,0) -> 20 | H9: =IF(F9 <= (G9/30)*20, "RUPTURA", IF(F9 < G9, "COMPRA IMEDIATA", IF(F9 > G9*2, "EXCESSO", "SAUDÁVEL"))) -> SAUDÁVEL | I9: 30 | J9: Caixa | K9: =IF(OR(H9="COMPRA IMEDIATA", H9="RUPTURA"), IF(ROUNDUP((MAX(IF(OR(C9="Copa",C9="Limpeza"), F9*2, F9*4), G9+F9) - F9) / I9, 0)<=0, "---", ROUNDUP((MAX(IF(OR(C9="Copa",C9="Limpeza"), F9*2, F9*4), G9+F9) - F9) / I9, 0) * I9 & " " & E9), "---") -> --- | L9: =IF(OR(H9="COMPRA IMEDIATA", H9="RUPTURA"), IF(K9="---", 0, _xlfn.XLOOKUP(B9, TBEstoque[SKU], TBEstoque[VALOR UNIT. (R$)]) * VALUE(LEFT(K9, SEARCH(" ", K9)-1))), "---") -> --- | M9: 46097 | N9: 15 | O9: =IF(OR(H9="COMPRA IMEDIATA", H9="RUPTURA"), WORKDAY(M9,N9,Feriados!$A$3:$A$19),"---") -> --- | Q9: =IFERROR(_xlfn.LET(_xlpm.f, _xlfn.XLOOKUP(D9, TBEstoque[DESCRIÇÃO], TBEstoque[FORNECEDOR], "---"), IF(_xlpm.f=0, "---", _xlpm.f)), "---") -> FORNECEDOR 05
B10: =TBEstoque[[#This Row],[SKU]] -> 20819 | C10: =IF(TBEstoque[[#This Row],[SKU]]=TBSuprimentos[[#This Row],[SKU]],TBEstoque[[#This Row],[CATEGÓRIA]]," ") -> Copa | D10: =IF(TBSuprimentos[[#This Row],[SKU]]=TBEstoque[[#This Row],[SKU]],TBEstoque[[#This Row],[DESCRIÇÃO]]," ") -> COPO DESCARTÁVEL 180ML (PCT) | E10: =IF(TBSuprimentos[[#This Row],[SKU]]=TBEstoque[[#This Row],[SKU]],TBEstoque[[#This Row],[UNID. MEDIDA]]," ") -> Pct | F10: =_xlfn.XLOOKUP(TBSuprimentos[[#This Row],[SKU]], TBEstoque[SKU], TBEstoque[ESTOQUE ATUAL], 0) - SUMIF(TBConsumo[SKU], TBSuprimentos[[#This Row],[SKU]], TBConsumo[QTDE SOLICITADA]) -> 121 | G10: =VLOOKUP(TBSuprimentos[[#This Row],[DESCRIÇÃO]],TBEstoque[[DESCRIÇÃO]:[CONSUMO MÉDIO MENSAL]],4,0) -> 50 | H10: =IF(F10 <= (G10/30)*20, "RUPTURA", IF(F10 < G10, "COMPRA IMEDIATA", IF(F10 > G10*2, "EXCESSO", "SAUDÁVEL"))) -> EXCESSO | I10: 25 | J10: Caixa | K10: =IF(OR(H10="COMPRA IMEDIATA", H10="RUPTURA"), IF(ROUNDUP((MAX(IF(OR(C10="Copa",C10="Limpeza"), F10*2, F10*4), G10+F10) - F10) / I10, 0)<=0, "---", ROUNDUP((MAX(IF(OR(C10="Copa",C10="Limpeza"), F10*2, F10*4), G10+F10) - F10) / I10, 0) * I10 & " " & E10), "---") -> --- | L10: =IF(OR(H10="COMPRA IMEDIATA", H10="RUPTURA"), IF(K10="---", 0, _xlfn.XLOOKUP(B10, TBEstoque[SKU], TBEstoque[VALOR UNIT. (R$)]) * VALUE(LEFT(K10, SEARCH(" ", K10)-1))), "---") -> --- | M10: 46097 | N10: 15 | O10: =IF(OR(H10="COMPRA IMEDIATA", H10="RUPTURA"), WORKDAY(M10,N10,Feriados!$A$3:$A$19),"---") -> --- | Q10: =IFERROR(_xlfn.LET(_xlpm.f, _xlfn.XLOOKUP(D10, TBEstoque[DESCRIÇÃO], TBEstoque[FORNECEDOR], "---"), IF(_xlpm.f=0, "---", _xlpm.f)), "---") -> FORNECEDOR 06
B11: =TBEstoque[[#This Row],[SKU]] -> 20820 | C11: =IF(TBEstoque[[#This Row],[SKU]]=TBSuprimentos[[#This Row],[SKU]],TBEstoque[[#This Row],[CATEGÓRIA]]," ") -> Copa | D11: =IF(TBSuprimentos[[#This Row],[SKU]]=TBEstoque[[#This Row],[SKU]],TBEstoque[[#This Row],[DESCRIÇÃO]]," ") -> COPO DESCARTÁVEL 80ML (PCT) | E11: =IF(TBSuprimentos[[#This Row],[SKU]]=TBEstoque[[#This Row],[SKU]],TBEstoque[[#This Row],[UNID. MEDIDA]]," ") -> Pct | F11: =_xlfn.XLOOKUP(TBSuprimentos[[#This Row],[SKU]], TBEstoque[SKU], TBEstoque[ESTOQUE ATUAL], 0) - SUMIF(TBConsumo[SKU], TBSuprimentos[[#This Row],[SKU]], TBConsumo[QTDE SOLICITADA]) -> 13 | G11: =VLOOKUP(TBSuprimentos[[#This Row],[DESCRIÇÃO]],TBEstoque[[DESCRIÇÃO]:[CONSUMO MÉDIO MENSAL]],4,0) -> 10 | H11: =IF(F11 <= (G11/30)*20, "RUPTURA", IF(F11 < G11, "COMPRA IMEDIATA", IF(F11 > G11*2, "EXCESSO", "SAUDÁVEL"))) -> SAUDÁVEL | I11: 25 | J11: Caixa | K11: =IF(OR(H11="COMPRA IMEDIATA", H11="RUPTURA"), IF(ROUNDUP((MAX(IF(OR(C11="Copa",C11="Limpeza"), F11*2, F11*4), G11+F11) - F11) / I11, 0)<=0, "---", ROUNDUP((MAX(IF(OR(C11="Copa",C11="Limpeza"), F11*2, F11*4), G11+F11) - F11) / I11, 0) * I11 & " " & E11), "---") -> --- | L11: =IF(OR(H11="COMPRA IMEDIATA", H11="RUPTURA"), IF(K11="---", 0, _xlfn.XLOOKUP(B11, TBEstoque[SKU], TBEstoque[VALOR UNIT. (R$)]) * VALUE(LEFT(K11, SEARCH(" ", K11)-1))), "---") -> --- | M11: 46097 | N11: 15 | O11: =IF(OR(H11="COMPRA IMEDIATA", H11="RUPTURA"), WORKDAY(M11,N11,Feriados!$A$3:$A$19),"---") -> --- | Q11: =IFERROR(_xlfn.LET(_xlpm.f, _xlfn.XLOOKUP(D11, TBEstoque[DESCRIÇÃO], TBEstoque[FORNECEDOR], "---"), IF(_xlpm.f=0, "---", _xlpm.f)), "---") -> FORNECEDOR 07
B12: =TBEstoque[[#This Row],[SKU]] -> 20821 | C12: =IF(TBEstoque[[#This Row],[SKU]]=TBSuprimentos[[#This Row],[SKU]],TBEstoque[[#This Row],[CATEGÓRIA]]," ") -> Copa | D12: =IF(TBSuprimentos[[#This Row],[SKU]]=TBEstoque[[#This Row],[SKU]],TBEstoque[[#This Row],[DESCRIÇÃO]]," ") -> LEITE EM PÓ 400 G (UNID) | E12: =IF(TBSuprimentos[[#This Row],[SKU]]=TBEstoque[[#This Row],[SKU]],TBEstoque[[#This Row],[UNID. MEDIDA]]," ") -> Pct | F12: =_xlfn.XLOOKUP(TBSuprimentos[[#This Row],[SKU]], TBEstoque[SKU], TBEstoque[ESTOQUE ATUAL], 0) - SUMIF(TBConsumo[SKU], TBSuprimentos[[#This Row],[SKU]], TBConsumo[QTDE SOLICITADA]) -> 164 | G12: =VLOOKUP(TBSuprimentos[[#This Row],[DESCRIÇÃO]],TBEstoque[[DESCRIÇÃO]:[CONSUMO MÉDIO MENSAL]],4,0) -> 200 | H12: =IF(F12 <= (G12/30)*20, "RUPTURA", IF(F12 < G12, "COMPRA IMEDIATA", IF(F12 > G12*2, "EXCESSO", "SAUDÁVEL"))) -> COMPRA IMEDIATA | I12: 25 | J12: Fardo | K12: =IF(OR(H12="COMPRA IMEDIATA", H12="RUPTURA"), IF(ROUNDUP((MAX(IF(OR(C12="Copa",C12="Limpeza"), F12*2, F12*4), G12+F12) - F12) / I12, 0)<=0, "---", ROUNDUP((MAX(IF(OR(C12="Copa",C12="Limpeza"), F12*2, F12*4), G12+F12) - F12) / I12, 0) * I12 & " " & E12), "---") -> 200 Pct | L12: =IF(OR(H12="COMPRA IMEDIATA", H12="RUPTURA"), IF(K12="---", 0, _xlfn.XLOOKUP(B12, TBEstoque[SKU], TBEstoque[VALOR UNIT. (R$)]) * VALUE(LEFT(K12, SEARCH(" ", K12)-1))), "---") -> 5520 | M12: 46097 | N12: 15 | O12: =IF(OR(H12="COMPRA IMEDIATA", H12="RUPTURA"), WORKDAY(M12,N12,Feriados!$A$3:$A$19),"---") -> 46119 | Q12: =IFERROR(_xlfn.LET(_xlpm.f, _xlfn.XLOOKUP(D12, TBEstoque[DESCRIÇÃO], TBEstoque[FORNECEDOR], "---"), IF(_xlpm.f=0, "---", _xlpm.f)), "---") -> FORNECEDOR 08
B13: =TBEstoque[[#This Row],[SKU]] -> 832 | C13: =IF(TBEstoque[[#This Row],[SKU]]=TBSuprimentos[[#This Row],[SKU]],TBEstoque[[#This Row],[CATEGÓRIA]]," ") -> Expedição | D13: =IF(TBSuprimentos[[#This Row],[SKU]]=TBEstoque[[#This Row],[SKU]],TBEstoque[[#This Row],[DESCRIÇÃO]]," ") -> ÁGUA DESMINERALIZADA 5 LT | E13: =IF(TBSuprimentos[[#This Row],[SKU]]=TBEstoque[[#This Row],[SKU]],TBEstoque[[#This Row],[UNID. MEDIDA]]," ") -> Gl | F13: =_xlfn.XLOOKUP(TBSuprimentos[[#This Row],[SKU]], TBEstoque[SKU], TBEstoque[ESTOQUE ATUAL], 0) - SUMIF(TBConsumo[SKU], TBSuprimentos[[#This Row],[SKU]], TBConsumo[QTDE SOLICITADA]) -> 10 | G13: =VLOOKUP(TBSuprimentos[[#This Row],[DESCRIÇÃO]],TBEstoque[[DESCRIÇÃO]:[CONSUMO MÉDIO MENSAL]],4,0) -> 1 | H13: =IF(F13 <= (G13/30)*20, "RUPTURA", IF(F13 < G13, "COMPRA IMEDIATA", IF(F13 > G13*2, "EXCESSO", "SAUDÁVEL"))) -> EXCESSO | I13: 1 | J13: Unidade | K13: =IF(OR(H13="COMPRA IMEDIATA", H13="RUPTURA"), IF(ROUNDUP((MAX(IF(OR(C13="Copa",C13="Limpeza"), F13*2, F13*4), G13+F13) - F13) / I13, 0)<=0, "---", ROUNDUP((MAX(IF(OR(C13="Copa",C13="Limpeza"), F13*2, F13*4), G13+F13) - F13) / I13, 0) * I13 & " " & E13), "---") -> --- | L13: =IF(OR(H13="COMPRA IMEDIATA", H13="RUPTURA"), IF(K13="---", 0, _xlfn.XLOOKUP(B13, TBEstoque[SKU], TBEstoque[VALOR UNIT. (R$)]) * VALUE(LEFT(K13, SEARCH(" ", K13)-1))), "---") -> --- | M13: 46097 | N13: 15 | O13: =IF(OR(H13="COMPRA IMEDIATA", H13="RUPTURA"), WORKDAY(M13,N13,Feriados!$A$3:$A$19),"---") -> --- | Q13: =IFERROR(_xlfn.LET(_xlpm.f, _xlfn.XLOOKUP(D13, TBEstoque[DESCRIÇÃO], TBEstoque[FORNECEDOR], "---"), IF(_xlpm.f=0, "---", _xlpm.f)), "---") -> FORNECEDOR 09
B14: =TBEstoque[[#This Row],[SKU]] -> 20822 | C14: =IF(TBEstoque[[#This Row],[SKU]]=TBSuprimentos[[#This Row],[SKU]],TBEstoque[[#This Row],[CATEGÓRIA]]," ") -> Expedição | D14: =IF(TBSuprimentos[[#This Row],[SKU]]=TBEstoque[[#This Row],[SKU]],TBEstoque[[#This Row],[DESCRIÇÃO]]," ") -> BOBINA MANTA BOLHA ALMOFADA MAQUINA WORLD POST (UNID) | E14: =IF(TBSuprimentos[[#This Row],[SKU]]=TBEstoque[[#This Row],[SKU]],TBEstoque[[#This Row],[UNID. MEDIDA]]," ") -> Unid | F14: =_xlfn.XLOOKUP(TBSuprimentos[[#This Row],[SKU]], TBEstoque[SKU], TBEstoque[ESTOQUE ATUAL], 0) - SUMIF(TBConsumo[SKU], TBSuprimentos[[#This Row],[SKU]], TBConsumo[QTDE SOLICITADA]) -> 15 | G14: =VLOOKUP(TBSuprimentos[[#This Row],[DESCRIÇÃO]],TBEstoque[[DESCRIÇÃO]:[CONSUMO MÉDIO MENSAL]],4,0) -> 5 | H14: =IF(F14 <= (G14/30)*20, "RUPTURA", IF(F14 < G14, "COMPRA IMEDIATA", IF(F14 > G14*2, "EXCESSO", "SAUDÁVEL"))) -> EXCESSO | I14: 1 | J14: Unidade | K14: =IF(OR(H14="COMPRA IMEDIATA", H14="RUPTURA"), IF(ROUNDUP((MAX(IF(OR(C14="Copa",C14="Limpeza"), F14*2, F14*4), G14+F14) - F14) / I14, 0)<=0, "---", ROUNDUP((MAX(IF(OR(C14="Copa",C14="Limpeza"), F14*2, F14*4), G14+F14) - F14) / I14, 0) * I14 & " " & E14), "---") -> --- | L14: =IF(OR(H14="COMPRA IMEDIATA", H14="RUPTURA"), IF(K14="---", 0, _xlfn.XLOOKUP(B14, TBEstoque[SKU], TBEstoque[VALOR UNIT. (R$)]) * VALUE(LEFT(K14, SEARCH(" ", K14)-1))), "---") -> --- | M14: 46097 | N14: 15 | O14: =IF(OR(H14="COMPRA IMEDIATA", H14="RUPTURA"), WORKDAY(M14,N14,Feriados!$A$3:$A$19),"---") -> --- | Q14: =IFERROR(_xlfn.LET(_xlpm.f, _xlfn.XLOOKUP(D14, TBEstoque[DESCRIÇÃO], TBEstoque[FORNECEDOR], "---"), IF(_xlpm.f=0, "---", _xlpm.f)), "---") -> FORNECEDOR 10
B15: =TBEstoque[[#This Row],[SKU]] -> 20824 | C15: =IF(TBEstoque[[#This Row],[SKU]]=TBSuprimentos[[#This Row],[SKU]],TBEstoque[[#This Row],[CATEGÓRIA]]," ") -> Expedição | D15: =IF(TBSuprimentos[[#This Row],[SKU]]=TBEstoque[[#This Row],[SKU]],TBEstoque[[#This Row],[DESCRIÇÃO]]," ") -> CAIXA PAPELÃO PARDA Nº00 (UNID) | E15: =IF(TBSuprimentos[[#This Row],[SKU]]=TBEstoque[[#This Row],[SKU]],TBEstoque[[#This Row],[UNID. MEDIDA]]," ") -> Unid | F15: =_xlfn.XLOOKUP(TBSuprimentos[[#This Row],[SKU]], TBEstoque[SKU], TBEstoque[ESTOQUE ATUAL], 0) - SUMIF(TBConsumo[SKU], TBSuprimentos[[#This Row],[SKU]], TBConsumo[QTDE SOLICITADA]) -> 20000 | G15: =VLOOKUP(TBSuprimentos[[#This Row],[DESCRIÇÃO]],TBEstoque[[DESCRIÇÃO]:[CONSUMO MÉDIO MENSAL]],4,0) -> 10000 | H15: =IF(F15 <= (G15/30)*20, "RUPTURA", IF(F15 < G15, "COMPRA IMEDIATA", IF(F15 > G15*2, "EXCESSO", "SAUDÁVEL"))) -> SAUDÁVEL | I15: 30 | J15: Fardo | K15: =IF(OR(H15="COMPRA IMEDIATA", H15="RUPTURA"), IF(ROUNDUP((MAX(IF(OR(C15="Copa",C15="Limpeza"), F15*2, F15*4), G15+F15) - F15) / I15, 0)<=0, "---", ROUNDUP((MAX(IF(OR(C15="Copa",C15="Limpeza"), F15*2, F15*4), G15+F15) - F15) / I15, 0) * I15 & " " & E15), "---") -> --- | L15: =IF(OR(H15="COMPRA IMEDIATA", H15="RUPTURA"), IF(K15="---", 0, _xlfn.XLOOKUP(B15, TBEstoque[SKU], TBEstoque[VALOR UNIT. (R$)]) * VALUE(LEFT(K15, SEARCH(" ", K15)-1))), "---") -> --- | M15: 46097 | N15: 30 | O15: =IF(OR(H15="COMPRA IMEDIATA", H15="RUPTURA"), WORKDAY(M15,N15,Feriados!$A$3:$A$19),"---") -> --- | Q15: =IFERROR(_xlfn.LET(_xlpm.f, _xlfn.XLOOKUP(D15, TBEstoque[DESCRIÇÃO], TBEstoque[FORNECEDOR], "---"), IF(_xlpm.f=0, "---", _xlpm.f)), "---") -> FORNECEDOR 11
B16: =TBEstoque[[#This Row],[SKU]] -> 20825 | C16: =IF(TBEstoque[[#This Row],[SKU]]=TBSuprimentos[[#This Row],[SKU]],TBEstoque[[#This Row],[CATEGÓRIA]]," ") -> Expedição | D16: =IF(TBSuprimentos[[#This Row],[SKU]]=TBEstoque[[#This Row],[SKU]],TBEstoque[[#This Row],[DESCRIÇÃO]]," ") -> CAIXA PAPELÃO PARDA Nº01 (UNID) | E16: =IF(TBSuprimentos[[#This Row],[SKU]]=TBEstoque[[#This Row],[SKU]],TBEstoque[[#This Row],[UNID. MEDIDA]]," ") -> Unid | F16: =_xlfn.XLOOKUP(TBSuprimentos[[#This Row],[SKU]], TBEstoque[SKU], TBEstoque[ESTOQUE ATUAL], 0) - SUMIF(TBConsumo[SKU], TBSuprimentos[[#This Row],[SKU]], TBConsumo[QTDE SOLICITADA]) -> 15600 | G16: =VLOOKUP(TBSuprimentos[[#This Row],[DESCRIÇÃO]],TBEstoque[[DESCRIÇÃO]:[CONSUMO MÉDIO MENSAL]],4,0) -> 8000 | H16: =IF(F16 <= (G16/30)*20, "RUPTURA", IF(F16 < G16, "COMPRA IMEDIATA", IF(F16 > G16*2, "EXCESSO", "SAUDÁVEL"))) -> SAUDÁVEL | I16: 25 | J16: Fardo | K16: =IF(OR(H16="COMPRA IMEDIATA", H16="RUPTURA"), IF(ROUNDUP((MAX(IF(OR(C16="Copa",C16="Limpeza"), F16*2, F16*4), G16+F16) - F16) / I16, 0)<=0, "---", ROUNDUP((MAX(IF(OR(C16="Copa",C16="Limpeza"), F16*2, F16*4), G16+F16) - F16) / I16, 0) * I16 & " " & E16), "---") -> --- | L16: =IF(OR(H16="COMPRA IMEDIATA", H16="RUPTURA"), IF(K16="---", 0, _xlfn.XLOOKUP(B16, TBEstoque[SKU], TBEstoque[VALOR UNIT. (R$)]) * VALUE(LEFT(K16, SEARCH(" ", K16)-1))), "---") -> --- | M16: 46097 | N16: 30 | O16: =IF(OR(H16="COMPRA IMEDIATA", H16="RUPTURA"), WORKDAY(M16,N16,Feriados!$A$3:$A$19),"---") -> --- | Q16: =IFERROR(_xlfn.LET(_xlpm.f, _xlfn.XLOOKUP(D16, TBEstoque[DESCRIÇÃO], TBEstoque[FORNECEDOR], "---"), IF(_xlpm.f=0, "---", _xlpm.f)), "---") -> FORNECEDOR 12
... B108: =TBEstoque[[#This Row],[SKU]] -> 20880 | C108: =IF(TBEstoque[[#This Row],[SKU]]=TBSuprimentos[[#This Row],[SKU]],TBEstoque[[#This Row],[CATEGÓRIA]]," ") -> Limpeza | D108: =IF(TBSuprimentos[[#This Row],[SKU]]=TBEstoque[[#This Row],[SKU]],TBEstoque[[#This Row],[DESCRIÇÃO]]," ") -> VEJA MULTIUSO (UNI) | E108: =IF(TBSuprimentos[[#This Row],[SKU]]=TBEstoque[[#This Row],[SKU]],TBEstoque[[#This Row],[UNID. MEDIDA]]," ") -> Unid | F108: =_xlfn.XLOOKUP(TBSuprimentos[[#This Row],[SKU]], TBEstoque[SKU], TBEstoque[ESTOQUE ATUAL], 0) - SUMIF(TBConsumo[SKU], TBSuprimentos[[#This Row],[SKU]], TBConsumo[QTDE SOLICITADA]) -> 24 | G108: =VLOOKUP(TBSuprimentos[[#This Row],[DESCRIÇÃO]],TBEstoque[[DESCRIÇÃO]:[CONSUMO MÉDIO MENSAL]],4,0) -> 30 | H108: =IF(F108 <= (G108/30)*20, "RUPTURA", IF(F108 < G108, "COMPRA IMEDIATA", IF(F108 > G108*2, "EXCESSO", "SAUDÁVEL"))) -> COMPRA IMEDIATA | I108: 1 | J108: Cx | K108: =IF(OR(H108="COMPRA IMEDIATA", H108="RUPTURA"), IF(ROUNDUP((MAX(IF(OR(C108="Copa",C108="Limpeza"), F108*2, F108*4), G108+F108) - F108) / I108, 0)<=0, "---", ROUNDUP((MAX(IF(OR(C108="Copa",C108="Limpeza"), F108*2, F108*4), G108+F108) - F108) / I108, 0) * I108 & " " & E108), "---") -> 30 Unid | L108: =IF(OR(H108="COMPRA IMEDIATA", H108="RUPTURA"), IF(K108="---", 0, _xlfn.XLOOKUP(B108, TBEstoque[SKU], TBEstoque[VALOR UNIT. (R$)]) * VALUE(LEFT(K108, SEARCH(" ", K108)-1))), "---") -> 274.275 | M108: 46097 | N108: 15 | O108: =IF(OR(H108="COMPRA IMEDIATA", H108="RUPTURA"), WORKDAY(M108,N108,Feriados!$A$3:$A$19),"---") -> 46119 | Q108: =IFERROR(_xlfn.LET(_xlpm.f, _xlfn.XLOOKUP(D108, TBEstoque[DESCRIÇÃO], TBEstoque[FORNECEDOR], "---"), IF(_xlpm.f=0, "---", _xlpm.f)), "---") -> FORNECEDOR 03

Sheet Validação de Dados
B1: Adm | C1: Copa | D1: Expedição | E1: Laboratório | F1: Limpeza
B2: FOLHA DE SULFITE A4 PACOTE | C2: AÇÚCAR (UNID) PACOTE 1 KG | D2: BOBINA MANTA BOLHA ALMOFADA MAQUINA WORLD POST (UNID) | E2: ABRAÇADEIRA DE NYLON PRETA (PCT C/100) | F2: ÁGUA SANITARIA SUPER CANDIDA GALÃO 5 LTS
B3: FOLHA DE SULFITE A5 PACOTE | C3: CAFÉ EM GRÃO MÁQUINA (UNID) | D3: CAIXA PAPELÃO PARDA Nº00 (UNID) | E3: AVENTAL DESCARTÁVEL PCT C/ 10 UNIDADES | F3: BOM AR
C4: CAFÉ EM PÓ (UNID) PACOTE 500 GRAMAS | D4: CAIXA PAPELÃO PARDA Nº01 (UNID) | E4: BOBINA CUPOM FISCAL BRANCA OFICIAL FARMA (CX) | F4: DESINFETANTE FLORAL GALÃO 5 LTS
C5: CHOCOLATE EM PÓ 1KG (UNID) | D5: CAIXA PAPELÃO PARDA Nº02 (UNID) | E5: Envelope Premiun TNT G | F5: DESINFETANTE LAVANDA GALÃO 5 LTS
C6: COPO DESCARTÁVEL 160ML (PCT) | D6: CAIXA PAPELÃO PARDA Nº03 (UNID) | E6: Envelope Premiun TNT P | F6: DETERGENTE LÍQUIDO YPÊ CLEAR GALÃO 5L
C7: COPO DESCARTÁVEL 180ML (PCT) | D7: CAIXA PAPELÃO PARDA Nº04 (UNID) | E7: FRASCO DESCARTÁVEL Y | F7: ESPONJA DUPLA FACE 3M (UNI)
C8: COPO DESCARTÁVEL 80ML (PCT) | D8: CAIXA PAPELÃO PARDA Nº05 (UNID) | E8: LUVA COM PÓ G LATEX (CX) | F8: FLANELA BRANCA (UNI)
C9: LEITE EM PÓ 400 G (UNID) | D9: CAIXA TERMICA 3L (UNID) | E9: Luva Com Pó M Latex (Cx) | F9: LUSTRA MÓVEIS
D10: CAIXA TERMICA 5L (UNID) | E10: LUVA COM PÓ P LATEX (CX) | F10: LUSTRA MÓVEIS POLIFLOR (UNI)
D11: CAIXA TERMICA 7L (UNID) | E11: LUVA COM PÓ PP LATEX (CX) | F11: LUVA AMARELA TAM: G (PARES)
D12: ENVELOPE COM BOLHA M (UNID) | E12: LUVA SEM PÓ G LATEX (CX) | F12: LUVA AMARELA TAM: GG (PARES)
D13: ENVELOPE COM BOLHA P (UNID) | E13: LUVA SEM PÓ M LATEX (CX) | F13: LUVA AMARELA TAM: M (PARES)
D14: ENVELOPE SEM BOLHA M (UNID) | E14: LUVA SEM PÓ P LATEX (CX) | F14: LUVA AMARELA TAM: P (PARES)
D15: ENVELOPE SEM BOLHA P (UNID) | E15: LUVA SEM PÓ PP LATEX (CX) | F15: LUVA AZUL TAM: G (PARES)
D16: ETIQUETA 100X100 BOPP ROLO | E16: MÁSCARA DESCARTÁVEL | F16: Luva Azul Tam: GG (PARES)
D17: ETIQUETA 100X100 COUCHE ROLO C/350 | E17: MÁSCARA Nº95 - UNIDADE | F17: LUVA AZUL TAM: M (PARES)
D18: ETIQUETA 100X30 BOPP ROLO | E18: MÁSCARA TRIPLA DESCARTÁVEL (CAIXA 50 UNI) | F18: LUVA AZUL TAM: P (PARES)
D19: FITA GOMADA 80MM(C/1,4 KGX160M) (CAIXA C/ 12 ROLOS) | E19: PACOTE SACHÊ 7X12 (CX C/1000) | F19: PANO DE CHÃO BRANCO ALVEJADO (UNI)
D20: FITA OFICIAL FARMA 48 X 100M (UNID) | E20: PACOTE SACHÊ 7X7 (CX C/1000) | F20: PANO DE CHÃO XADREZ (UNI)
D21: FITA TRANSPARENTE 48 X 100M (UNI) | E21: PAPEL MULTIUSO INTERFOLHADO DEMARCARE NEVE | F21: PANO DE PRATO (UNI)
... D25: RIBBON CERÂ (PCT C/ 2) - (UNID) | E25: RÓTULO R.FIGUEIRAS - 100X30 - LATERAL - ROLO | F25: PAPEL TOALHA OUROPPEL COM 8 ROLOS (CX)
E26: SACO PLASTICO 10X15 (PCT) | F26: PEDRA SANITÁRIA (UNI)
E27: SACO PLASTICO 15X25 (PCT) | F27: SABÃO EM PEDRA (UNI)
E28: SACO PLASTICO 20X30 (PCT) | F28: SABÃO EM PÓ TRIPLAÇÃO (CX)
E29: SACO PLASTICO 30X40 (PCT) | F29: SABONETE LÍQUIDO 5 LTS (UNI)
E30: SACO PLASTICO 40X60 (PCT) | F30: SACO PARA LIXO BRANCO 100L (PCT)
E31: SACOLA G 40X55 + 10CMX0,15MM (SOPLAST) | F31: SACO PARA LIXO BRANCO 20L (PCT)
E32: SACOLA P 17,5X25 + 3CMX0,13MM (SOPLAST) | F32: SACO PARA LIXO BRANCO 40L (PCT)
E33: SONTARA (UNI) | F33: SACO PARA LIXO BRANCO 60L (PCT)
E34: TOUCA SANFONADA BRANCO DESCARTÁVEL (PCT C/100) | F34: SACO PARA LIXO PRETO 100L (PCT)
F35: SACO PARA LIXO PRETO 20L (PCT)
F36: SACO PARA LIXO PRETO 40L (PCT)
F37: SACO PARA LIXO PRETO 60L (PCT)
F38: SAPÓLIO CREMOSO
F39: SAPOLIO CREMOSO MULTIUSO (UNI)
F40: VEJA MULTIUSO (UNI)

Sheet Feriados
A2: Data | B2: Dia da Semana | C2: Feriado
A3: 46023 | B3: Quinta-feira | C3: Confraternização Universal
A4: 46069 | B4: Segunda-feira | C4: Carnaval (Ponto Facultativo)
A5: 46070 | B5: Terça-feira | C5: Carnaval (Ponto Facultativo)
A6: 46071 | B6: Quarta-feira | C6: Quarta-feira de Cinzas (Ponto Facultativo até 14h)
A7: 46115 | B7: Sexta-feira | C7: Sexta-feira Santa
A8: 46117 | B8: Domingo | C8: Páscoa
A9: 46133 | B9: Terça-feira | C9: Tiradentes
A10: 46143 | B10: Sexta-feira | C10: Dia do Trabalho
A11: 46177 | B11: Quinta-feira | C11: Corpus Christi (Ponto Facultativo)
A12: 46212 | B12: Quinta-feira | C12: Revolução Constitucionalista (Estadual SP)
A13: 46272 | B13: Segunda-feira | C13: Independência do Brasil
A14: 46307 | B14: Segunda-feira | C14: Nossa Sra. Aparecida
... A19: 46381 | B19: Sexta-feira | C19: Natal

Sheet Análise
C7: Qual a nossa eficiência em manter o que é vital disponível?
C8: O índice de 100% mascara excesso de capital imobilizado. Ação estratégica: parametrizamos o ressuprimento por categoria.
C9: Copa/Limpeza caem para 30 dias de cobertura (+15 de lead time), enquanto Produção/Expedição mantêm 90 dias (+30 de lead time). Otimiza-se o caixa sem risco de ruptura.
C11: Nível de Serviço Essencial (%)
C12: 1
C14: Quanto dinheiro temos parado em itens que não giram (Classe C)?
C15: Este valor refere-se especificamente aos itens que não giram e estão travados no estoque.
C16: R$ 17.583,65 parados em itens sem giro. Ação imediata: transferência de saldo entre unidades para forçar o consumo.
C17: Ação preventiva: o ERP passará a operar com estoque mínimo restrito para a Classe C, liberando compras apenas para picos sazonais ou urgências.
C19: Capital Imobilizado Crítico (R$)
C20: 17938.646
C22: Por quanto tempo nossa operação sobrevive com o que temos hoje?
C23: Fim da reposição por "achismo". O gatilho de "Compra Imediata" agora é dinâmico, cruzando o saldo com o lead time específico da categoria (15 ou 30 dias úteis).
C24: O sistema automatiza o pedido no timing exato, blindando a operação sem inflar o estoque.
C26: Cobertura de Estoque (Dias)
C27: 90.815795
C29: O que estamos consumindo está dentro do planejado ou há desperdício?
C30: O baixo índice indica requisições descontroladas que forçam fretes emergenciais. Ação: auditoria nos setores ofensores via Pareto e criação de trava sistêmica.
C31: Pedidos que desrespeitem o teto da sua categoria serão bloqueados e exigirão aprovação gerencial prévia.
C33: Aderência ao Consumo (%)
C34: 0.41594452
C36: Quais itens essenciais correm risco de ruptura imediata?
C37: Os itens essenciais estão comprados, mas o prazo de 15 dias úteis do fornecedor cria um buraco no estoque.
C38: A estratégia não é fazer compras pequenas, mas sim ajustar o próximo pedido mensal adicionando uma margem de segurança de 15 dias úteis extras,
C39: Isso garante que o estoque dure até a entrega do mês seguinte sem sustos
C40: Custo Total do Pedido de Compras do Mês de Fevereiro R$ 27.531,98
C42: ITEM ESSENCIAL | D42: SIM
C44: Máx. de SKU | D44: Rótulos de Coluna
C45: Descrição | D45: COMPRA IMEDIATA | E45: RUPTURA | F45: Total Geral
C46: AÇÚCAR (UNID) PACOTE 1 KG
C47: 340,98 | D47: 20814 | F47: 20814
C48: ÁGUA SANITARIA SUPER CANDIDA GALÃO 5 LTS
C49: 397,44 | D49: 20847 | F49: 20847
C50: DESINFETANTE FLORAL GALÃO 5 LTS
C51: 1.467,98 | D51: 20848 | F51: 20848
C52: FOLHA DE SULFITE A4 PACOTE
C53: 1.489,02 | E53: 20810 | F53: 20810
C54: LEITE EM PÓ 400 G (UNID)
C55: 5.520,00 | D55: 20821 | F55: 20821
C56: PANO DE CHÃO BRANCO ALVEJADO (UNI)
C57: 451,95 | D57: 20862 | F57: 20862
C58: PAPEL HIGIÊNICO ROLÃO C/ 8 BOBINAS DE 200M (CX)
C59: 15.029,35 | D59: 20812 | F59: 20812
C60: SACO PARA LIXO PRETO 100L (PCT)
C61: 2.691,00 | E61: 20876 | F61: 20876
C62: VEJA MULTIUSO (UNI)
C63: 274,28 | D63: 20880 | F63: 20880
C64: Total Geral | D64: 20880 | E64: 20876 | F64: 20880
C67: Onde o capital está preso sem necessidade (Excesso de Itens C)?
C68: O foco aqui é o eliminação inteligente, O saldo atual (como as luvas com pó) será transferido para as unidades das farmácias, expedição, almoxarifado e advanced,
C69: com o objetivo é queimar esse estoque em áreas onde o produto é aceito, recuperando o valor investido e evitando a perda total
C71: CURVA ABC | D71: C
C73: Descrição | D73: VALOR TOTAL (R$)
C74: Copa
C75: COPO DESCARTÁVEL 160ML (PCT) | D75: 499.675
C76: COPO DESCARTÁVEL 80ML (PCT) | D76: 149.7
C77: Expedição
C78: CAIXA TERMICA 7L (UNID) | D78: 2176.375
C79: Farmácia/Produção
C80: Luva Com Pó M Latex (Cx) | D80: 4669
C81: LUVA COM PÓ G LATEX (CX) | D81: 4002
C82: SACO PLASTICO 10X15 (PCT) | D82: 2173.5
C83: ETIQUETA 50X50 PARA SACHÊ | D83: 1857
C84: Limpeza
C85: SACO PARA LIXO PRETO 40L (PCT) | D85: 862.5
C86: SACO PARA LIXO BRANCO 20L (PCT) | D86: 506
C87: SABÃO EM PEDRA (UNI) | D87: 355.925
C88: SAPOLIO CREMOSO MULTIUSO (UNI) | D88: 299.69
C89: SACO PARA LIXO BRANCO 40L (PCT) | D89: 241.5
C90: LUVA AZUL TAM: G (PARES) | D90: 223.56
C91: LUVA AMARELA TAM: G (PARES) | D91: 168.36
C92: Luva Azul Tam: GG (PARES) | D92: 149.04
C93: LUVA AMARELA TAM: GG (PARES) | D93: 132.204
C94: PANO MULTIUSO AMARELO PCT- 2 UNIDADES (PCT) | D94: 121.992
C95: Total Geral | D95: 18588.021
C97: Como está distribuído o consumo de materiais por Unidade e qual o impacto financeiro de cada Solicitante no orçamento?
C98: Vou implementar um controle baseado na média de consumo dos últimos 3 meses
C99: Qualquer solicitação que ultrapasse essa média histórica será sinalizada como desvio para a gerência, impedindo o faturamento automático
C101: CATEGÓRIA | D101: All
C103: Descrição | D103: VALOR TOTAL (R$)
C104: Conferente de Carga
C105: CD Logística - Regional ABC | D105: 9568.92
C106: Auxiliar Operacional 02
C107: Planta Industrial - Suprimentos | D107: 9147.0195
C108: Auxiliar de Recebimento
C109: CD Logística - Regional ABC | D109: 8570.536
C110: Almoxarife Jr
C111: Planta Industrial - Suprimentos | D111: 8286.9575
C112: Analista Financeiro
C113: Escritório Apoio - Gestão | D113: 6184.4745
C114: Secretária Executiva
C115: Escritório Central - Sede | D115: 5563.5275
C116: Assistente Administrativo 04
C117: Farmácia Satélite - Unidade 03 | D117: 5531.243
C118: Gestor de Inventário
C119: Farmácia Principal - Unidade 01 | D119: 4475.3515
C120: Farmacêutico Pleno 01
C121: Farmácia Satélite - Unidade 02 | D121: 4427.8865
C122: Assistente Administrativo 01
C123: Farmácia Principal - Unidade 01 | D123: 4355.8435
...

Sheet Regras de negócio
A1: 1. Definição de KPIs (Indicadores Chave de Desempenho)
A3: Estes indicadores devem monitorar diretamente os dois pilares da dor do seu gestor: Falta e Excesso.
A5: KPI 1: Nível de Serviço de Itens Essenciais (%)
A9: O que mede: A porcentagem de itens marcados como "Essenciais" que possuem estoque acima do ponto de pedido.
A11: Objetivo: Manter o mais próximo possível de 100% para garantir que a operação não pare.
A13: KPI 2: Índice de Capital Imobilizado Crítico (R$)
A17: O que mede: O valor total em Reais parado em itens com status de "EXCESSO (>90 dias)" ou que pertençam à Classe C da Curva ABC.
A19: Objetivo: Reduzir este valor para liberar fluxo de caixa.
A21: KPI 3: Cobertura de Estoque por Categoria (Dias)
A25: O que mede: Quantos dias o estoque atual suporta a operação antes de zerar, calculado por categoria (Ex: Expedição vs. Copa).
A27: Objetivo: Evitar coberturas excessivas (desperdício) em itens não críticos e coberturas baixas em itens essenciais.
A29: KPI 4: Aderência ao Consumo Planejado (%)
... A73: Visual Recomendado: Cartão de destaque com o valor total de "Saving Estimado".
